{
  "type": "Feature",
  "properties": {
    "gn:admin1_code":"16",
    "gn:asciiname":"Bugant",
    "gn:country_code":"MN",
    "gn:dem":766,
    "gn:feature_class":"P",
    "gn:feature_code":"PPLA2",
    "gn:name":"Bugant",
    "gn:population":0,
    "gn:timezone":"Asia/Ulaanbaatar",
    "iso:country":"MN",
    "name:mon_x_preferred":[
        "Bugant"
    ],
    "name:und_x_variant":[
        "Y\u00f6r\u00f6\u00f6horoo",
        "Y\u00f6r\u00f6\u00f6 Khoroo"
    ],
    "wof:name":"Bugant",
    "wof:placetype":"locality"
},
  "geometry": {"coordinates":[106.84999999999999,49.58333],"type":"Point"}
}