{
  "type": "Feature",
  "properties": {
    "gn:admin1_code":"02",
    "gn:asciiname":"Erdenetsogt",
    "gn:cc2":"MN",
    "gn:country_code":"MN",
    "gn:dem":2075,
    "gn:feature_class":"P",
    "gn:feature_code":"PPLA2",
    "gn:name":"Erdenetsogt",
    "gn:population":0,
    "gn:timezone":"Asia/Ulaanbaatar",
    "iso:country":"MN",
    "name:und_x_variant":[
        "Erdeni Tsogtu",
        "Erdeni Tsogtu Sume",
        "Erdeni Tsogto Suma",
        "Erdeni Tsogtu Somon",
        "Erdeni tsogtu sumu"
    ],
    "wof:name":"Erdenetsogt",
    "wof:placetype":"locality"
},
  "geometry": {"coordinates":[100.82239,46.41845],"type":"Point"}
}