{
  "type": "Feature",
  "properties": {
    "gn:admin1_code":"02",
    "gn:asciiname":"Erdenetsogt",
    "gn:cc2":"MN",
    "gn:country_code":"MN",
    "gn:dem":2075,
    "gn:feature_class":"P",
    "gn:feature_code":"PPLA2",
    "gn:name":"Erdenetsogt",
    "gn:population":0,
    "gn:timezone":"Asia/Ulaanbaatar",
    "iso:country":"MN",
    "name:ceb_x_preferred":[
        "Erdenetsogt Sum"
    ],
    "name:mal_x_preferred":[
        "\u0d0e\u0d7c\u0d21\u0d46\u0d28\u0d46\u0d38\u0d4d\u0d31\u0d4d\u0d31\u0d4d\u0d38\u0d4b\u0d17\u0d4d\u0d21\u0d4d"
    ],
    "name:mkd_x_preferred":[
        "\u0415\u0440\u0434\u0435\u043d\u0435\u0446\u043e\u0433\u0442"
    ],
    "name:mon_x_preferred":[
        "\u042d\u0440\u0434\u044d\u043d\u044d\u0446\u043e\u0433\u0442 \u0441\u0443\u043c"
    ],
    "name:rus_x_preferred":[
        "\u042d\u0440\u0434\u044d\u043d\u044d\u0446\u043e\u0433\u0442"
    ],
    "name:ukr_x_preferred":[
        "\u0415\u0440\u0434\u0435\u043d\u0435\u0446\u043e\u0433\u0442"
    ],
    "name:und_x_variant":[
        "Erdeni Tsogtu",
        "Erdeni Tsogtu Sume",
        "Erdeni Tsogto Suma",
        "Erdeni Tsogtu Somon",
        "Erdeni tsogtu sumu"
    ],
    "wof:name":"Erdenetsogt",
    "wof:placetype":"locality"
},
  "geometry": {"coordinates":[100.82239,46.41845],"type":"Point"}
}