{
  "type": "Feature",
  "properties": {
    "gn:admin1_code":"17.0",
    "gn:asciiname":"Tsagaan Chuluutayn Hiid",
    "gn:cc2":"MN",
    "gn:country_code":"MN",
    "gn:dem":1158,
    "gn:feature_class":"P",
    "gn:feature_code":"PPL",
    "gn:name":"Tsagaan Chuluutayn Hiid",
    "gn:population":0,
    "gn:timezone":"Asia/Choibalsan",
    "iso:country":"MN",
    "name:und_x_variant":[
        "Tsagan-chulutyin Khid",
        "Tsagan chulutyyn khid",
        "Tsagan Chulut\u00f6yn Khid",
        "Tsagaan Chuluutayn Hiid"
    ],
    "wof:name":"Tsagaan Chuluutayn Hiid",
    "wof:placetype":"locality"
},
  "geometry": {"coordinates":[112.91667,47.08333],"type":"Point"}
}