{
  "type": "Feature",
  "properties": {
    "gn:admin1_code":"01",
    "gn:asciiname":"Doodo Boriljitoyn Dugang",
    "gn:cc2":"MN",
    "gn:country_code":"MN",
    "gn:dem":2098,
    "gn:feature_class":"P",
    "gn:feature_code":"PPL",
    "gn:name":"Doodo Boriljitoyn Dugang",
    "gn:population":0,
    "gn:timezone":"Asia/Ulaanbaatar",
    "iso:country":"MN",
    "name:und_x_variant":[
        "Dood boril\u2019chzhutuiin dugang",
        "Doodo-Borillitoyn-Dugan",
        "Dood boril\u2019chzhutiin dugang",
        "Doodo Boriljitoyn Dugang"
    ],
    "wof:name":"Doodo Boriljitoyn Dugang",
    "wof:placetype":"locality"
},
  "geometry": {"coordinates":[100.06667,48.21667],"type":"Point"}
}