{
  "type": "Feature",
  "properties": {
    "gn:admin1_code":"3.0",
    "gn:asciiname":"Beleu",
    "gn:cc2":"MN",
    "gn:country_code":"MN",
    "gn:dem":1792,
    "gn:feature_class":"P",
    "gn:feature_code":"PPL",
    "gn:name":"Beleu",
    "gn:population":0,
    "gn:timezone":"Asia/Hovd",
    "iso:country":"MN",
    "name:und_x_variant":[
        "Pieh-liu",
        "Bereu",
        "Belu",
        "Pieh-lieh-wu",
        "Beleu"
    ],
    "wof:name":"Beleu",
    "wof:placetype":"locality"
},
  "geometry": {"coordinates":[89.46666999999999,49.06667],"type":"Point"}
}