{
  "type": "Feature",
  "properties": {
    "gn:admin1_code":"1.0",
    "gn:asciiname":"Bulenii Huryee",
    "gn:cc2":"MN",
    "gn:country_code":"MN",
    "gn:dem":2468,
    "gn:feature_class":"P",
    "gn:feature_code":"PPL",
    "gn:name":"B\u00fclenii H\u00fcryee",
    "gn:population":0,
    "gn:timezone":"Asia/Ulaanbaatar",
    "iso:country":"MN",
    "name:und_x_variant":[
        "Buleni Khure",
        "B\u00fclenii H\u00fcryee"
    ],
    "wof:name":"Bulenii Huryee",
    "wof:placetype":"locality"
},
  "geometry": {"coordinates":[99.05,47.66667],"type":"Point"}
}