{
  "type": "Feature",
  "properties": {
    "gn:admin1_code":"08",
    "gn:asciiname":"Darhan Jisa",
    "gn:cc2":"MN",
    "gn:country_code":"MN",
    "gn:dem":1244,
    "gn:feature_class":"P",
    "gn:feature_code":"PPL",
    "gn:name":"Darhan Jisa",
    "gn:population":0,
    "gn:timezone":"Asia/Ulaanbaatar",
    "iso:country":"MN",
    "name:und_x_variant":[
        "Darakhin-jasa",
        "Darikhin-dzhasa",
        "Darikhin Chzhisa",
        "Darhan Jisa"
    ],
    "wof:name":"Darhan Jisa",
    "wof:placetype":"locality"
},
  "geometry": {"coordinates":[108.23333,46.33333],"type":"Point"}
}