{
  "type": "Feature",
  "properties": {
    "gn:admin1_code":"01",
    "gn:asciiname":"Muren Sumu",
    "gn:country_code":"MN",
    "gn:dem":1839,
    "gn:feature_class":"P",
    "gn:feature_code":"PPL",
    "gn:name":"Muren Sumu",
    "gn:population":0,
    "gn:timezone":"Asia/Ulaanbaatar",
    "iso:country":"MN",
    "name:und_x_variant":[
        "Muren somon",
        "M\u00f6r\u00f6n Sumu",
        "M\u00f6r\u00f6n Suma",
        "Muren",
        "M\u00f6r\u00f6n"
    ],
    "wof:name":"Muren Sumu",
    "wof:placetype":"locality"
},
  "geometry": {"coordinates":[100.37417000000001,48.26444],"type":"Point"}
}