{
  "type": "Feature",
  "properties": {
    "gn:admin1_code":"19.0",
    "gn:asciiname":"Haan Tuuheiin Huryee",
    "gn:cc2":"MN",
    "gn:country_code":"MN",
    "gn:dem":1921,
    "gn:feature_class":"P",
    "gn:feature_code":"PPL",
    "gn:name":"Haan T\u00fc\u00fcheiin H\u00fcryee",
    "gn:population":0,
    "gn:timezone":"Asia/Hovd",
    "iso:country":"MN",
    "name:und_x_variant":[
        "Khan tukhein khure",
        "Haan T\u00fc\u00fcheiin H\u00fcryee"
    ],
    "wof:name":"Haan Tuuheiin Huryee",
    "wof:placetype":"locality"
},
  "geometry": {"coordinates":[94.88333,49.28333],"type":"Point"}
}