{
  "type": "Feature",
  "properties": {
    "gn:admin1_code":"7.0",
    "gn:asciiname":"Nuden",
    "gn:country_code":"MN",
    "gn:dem":1015,
    "gn:feature_class":"P",
    "gn:feature_code":"PPLA2",
    "gn:name":"N\u00fcden",
    "gn:population":0,
    "gn:timezone":"Asia/Ulaanbaatar",
    "iso:country":"MN",
    "name:mon_x_preferred":[
        "N\u00fcden"
    ],
    "name:und_x_variant":[
        "Ulan-Badrakh",
        "Ulaan Badaraha Suma",
        "Ulan-badarakhu-Sumu",
        "Ulan Badarkhu Somon",
        "Ulaanbadrakh",
        "Ulaan Badaraha Sumu",
        "Ulan Badarakhu",
        "Ulaan badarahu",
        "Ulaan badarahu sumu",
        "Ulaanbadrah"
    ],
    "wof:name":"Nuden",
    "wof:placetype":"locality"
},
  "geometry": {"coordinates":[110.46666999999999,43.58333],"type":"Point"}
}