{
  "type": "Feature",
  "properties": {
    "gn:admin1_code":"13.0",
    "gn:asciiname":"Dzagdza Dugang",
    "gn:cc2":"MN",
    "gn:country_code":"MN",
    "gn:dem":1349,
    "gn:feature_class":"P",
    "gn:feature_code":"PPL",
    "gn:name":"Dzagdza Dugang",
    "gn:population":0,
    "gn:timezone":"Asia/Ulaanbaatar",
    "iso:country":"MN",
    "name:und_x_variant":[
        "Tsza-Tszu-Khure",
        "Dzagasata Dugan",
        "Tszagtszu dugang",
        "Dzagdza-dugan",
        "Dzagdza Dugang"
    ],
    "wof:name":"Dzagdza Dugang",
    "wof:placetype":"locality"
},
  "geometry": {"coordinates":[99.58333,49.61667],"type":"Point"}
}