{
  "type": "Feature",
  "properties": {
    "gn:admin1_code":"18",
    "gn:asciiname":"Mursan Hural",
    "gn:cc2":"MN",
    "gn:country_code":"MN",
    "gn:dem":1330,
    "gn:feature_class":"P",
    "gn:feature_code":"PPL",
    "gn:name":"Mursan Hural",
    "gn:population":0,
    "gn:timezone":"Asia/Ulaanbaatar",
    "iso:country":"MN",
    "name:und_x_variant":[
        "Marsun khural",
        "Mursun Khural",
        "Mursan Hural"
    ],
    "wof:name":"Mursan Hural",
    "wof:placetype":"locality"
},
  "geometry": {"coordinates":[104.59999999999999,47.41667],"type":"Point"}
}