{
  "type": "Feature",
  "properties": {
    "gn:admin1_code":"7.0",
    "gn:asciiname":"Toliin Dzoo Hiid",
    "gn:cc2":"MN",
    "gn:country_code":"MN",
    "gn:dem":1204,
    "gn:feature_class":"P",
    "gn:feature_code":"PPL",
    "gn:name":"Toliin Dzoo Hiid",
    "gn:population":0,
    "gn:timezone":"Asia/Ulaanbaatar",
    "iso:country":"MN",
    "name:und_x_variant":[
        "Tol\u00f6yn Tszo Khid",
        "Tolyyn tszo khid",
        "Toliin Dzoo Hiid"
    ],
    "wof:name":"Toliin Dzoo Hiid",
    "wof:placetype":"locality"
},
  "geometry": {"coordinates":[109.38333,43.01667],"type":"Point"}
}