{
  "type": "Feature",
  "properties": {
    "gn:admin1_code":"07",
    "gn:asciiname":"Bulangiin Hural",
    "gn:cc2":"MN",
    "gn:country_code":"MN",
    "gn:dem":931,
    "gn:feature_class":"P",
    "gn:feature_code":"PPL",
    "gn:name":"Bulangiin Hural",
    "gn:population":0,
    "gn:timezone":"Asia/Ulaanbaatar",
    "iso:country":"MN",
    "name:und_x_variant":[
        "Bulungyyn khural",
        "Bulangin",
        "Bulungin Khural",
        "Bulung\u00f6yn Khural",
        "Bulungin Khura",
        "Bulangiin Hural"
    ],
    "wof:name":"Bulangiin Hural",
    "wof:placetype":"locality"
},
  "geometry": {"coordinates":[111.16667,44.91667],"type":"Point"}
}