{
  "type": "Feature",
  "properties": {
    "gn:admin1_code":"14.0",
    "gn:asciiname":"Norboiin Salbari Horshoo",
    "gn:cc2":"MN",
    "gn:country_code":"MN",
    "gn:dem":1661,
    "gn:feature_class":"P",
    "gn:feature_code":"PPL",
    "gn:name":"Norboiin Salbari Horshoo",
    "gn:population":0,
    "gn:timezone":"Asia/Ulaanbaatar",
    "iso:country":"MN",
    "name:und_x_variant":[
        "Norboyn salour yurt",
        "Norbain salouri khorsho",
        "Norboyn Salour Horshoo",
        "Norboin salouri khorsho",
        "Norboiin Salbari Horshoo"
    ],
    "wof:name":"Norboiin Salbari Horshoo",
    "wof:placetype":"locality"
},
  "geometry": {"coordinates":[103.62972000000001,43.87222],"type":"Point"}
}