{
  "type": "Feature",
  "properties": {
    "gn:admin1_code":"16",
    "gn:asciiname":"Hujirta",
    "gn:cc2":"MN",
    "gn:country_code":"MN",
    "gn:dem":1100,
    "gn:feature_class":"P",
    "gn:feature_code":"PPL",
    "gn:name":"Hujirta",
    "gn:population":0,
    "gn:timezone":"Asia/Ulaanbaatar",
    "iso:country":"MN",
    "name:und_x_variant":[
        "Khuchzhirtu",
        "Hujirta"
    ],
    "wof:name":"Hujirta",
    "wof:placetype":"locality"
},
  "geometry": {"coordinates":[106.84999999999999,49.86667],"type":"Point"}
}