{
  "type": "Feature",
  "properties": {
    "gn:admin1_code":"9.0",
    "gn:asciiname":"Tegshiin Huryee",
    "gn:cc2":"MN",
    "gn:country_code":"MN",
    "gn:dem":2038,
    "gn:feature_class":"P",
    "gn:feature_code":"PPL",
    "gn:name":"Tegshiin H\u00fcryee",
    "gn:population":0,
    "gn:timezone":"Asia/Hovd",
    "iso:country":"MN",
    "name:und_x_variant":[
        "Tegshiin khure",
        "Tegshiin H\u00fcryee"
    ],
    "wof:name":"Tegshiin Huryee",
    "wof:placetype":"locality"
},
  "geometry": {"coordinates":[95.98333,48.75],"type":"Point"}
}