{
  "type": "Feature",
  "properties": {
    "gn:admin1_code":"13",
    "gn:asciiname":"Bulag",
    "gn:cc2":"MN",
    "gn:country_code":"MN",
    "gn:dem":1531,
    "gn:feature_class":"P",
    "gn:feature_code":"PPLA2",
    "gn:name":"Bulag",
    "gn:population":0,
    "gn:timezone":"Asia/Ulaanbaatar",
    "iso:country":"MN",
    "name:eng_x_preferred":[
        "Bulag"
    ],
    "name:rus_x_preferred":[
        "\u0422\u0443\u043d\u044d\u043b"
    ],
    "name:und_x_variant":[
        "T\u00fcnel"
    ],
    "wof:name":"Bulag",
    "wof:placetype":"locality"
},
  "geometry": {"coordinates":[100.62687,49.85946],"type":"Point"}
}