{
  "type": "Feature",
  "properties": {
    "gn:admin1_code":"13",
    "gn:asciiname":"Bulag",
    "gn:cc2":"MN",
    "gn:country_code":"MN",
    "gn:dem":1531,
    "gn:feature_class":"P",
    "gn:feature_code":"PPLA2",
    "gn:name":"Bulag",
    "gn:population":0,
    "gn:timezone":"Asia/Ulaanbaatar",
    "iso:country":"MN",
    "name:eng_x_preferred":[
        "Bulag"
    ],
    "name:fas_x_preferred":[
        "\u062a\u0648\u0646\u0644"
    ],
    "name:fra_x_preferred":[
        "T\u00fcnel"
    ],
    "name:gle_x_preferred":[
        "T\u00fcnel"
    ],
    "name:mkd_x_preferred":[
        "\u0422\u0443\u043d\u0435\u043b"
    ],
    "name:mon_x_preferred":[
        "\u0422\u04af\u043d\u044d\u043b \u0441\u0443\u043c"
    ],
    "name:rus_x_preferred":[
        "\u0422\u0443\u043d\u044d\u043b"
    ],
    "name:ukr_x_preferred":[
        "\u0422\u0443\u043d\u0435\u043b"
    ],
    "wof:name":"Bulag",
    "wof:placetype":"locality"
},
  "geometry": {"coordinates":[100.62687,49.85946],"type":"Point"}
}