{
  "type": "Feature",
  "properties": {
    "gn:admin1_code":"10.0",
    "gn:asciiname":"Togrog",
    "gn:cc2":"MN",
    "gn:country_code":"MN",
    "gn:dem":1676,
    "gn:feature_class":"P",
    "gn:feature_code":"PPLA2",
    "gn:name":"T\u00f6gr\u00f6g",
    "gn:population":0,
    "gn:timezone":"Asia/Hovd",
    "iso:country":"MN",
    "name:und_x_variant":[
        "Tugurig Sume",
        "Tugurig somon",
        "T\u00fcg\u00fcrig sumu",
        "Torog",
        "Tugurig",
        "Tugurik",
        "T\u00f6g\u00f6rig",
        "Tugurik Somon",
        "T\u00f6g\u00f6rig Suma"
    ],
    "wof:name":"Togrog",
    "wof:placetype":"locality"
},
  "geometry": {"coordinates":[94.81544,45.82976],"type":"Point"}
}