{
  "type": "Feature",
  "properties": {
    "gn:admin1_code":"3.0",
    "gn:asciiname":"Uliast",
    "gn:country_code":"MN",
    "gn:dem":1317,
    "gn:feature_class":"P",
    "gn:feature_code":"PPL",
    "gn:name":"Uliast",
    "gn:population":0,
    "gn:timezone":"Asia/Hovd",
    "iso:country":"MN",
    "wof:name":"Uliast",
    "wof:placetype":"locality"
},
  "geometry": {"coordinates":[91.25,48.91667],"type":"Point"}
}