{
  "type": "Feature",
  "properties": {
    "gn:admin1_code":"21.0",
    "gn:asciiname":"Toli Hural",
    "gn:cc2":"MN",
    "gn:country_code":"MN",
    "gn:dem":1291,
    "gn:feature_class":"P",
    "gn:feature_code":"PPL",
    "gn:name":"Toli Hural",
    "gn:population":0,
    "gn:timezone":"Asia/Ulaanbaatar",
    "iso:country":"MN",
    "name:und_x_variant":[
        "Toli Khural",
        "Toli Hural"
    ],
    "wof:name":"Toli Hural",
    "wof:placetype":"locality"
},
  "geometry": {"coordinates":[103.25,47.93333],"type":"Point"}
}