{
  "type": "Feature",
  "properties": {
    "gn:admin1_code":"9.0",
    "gn:asciiname":"Shiree",
    "gn:cc2":"MN",
    "gn:country_code":"MN",
    "gn:dem":1828,
    "gn:feature_class":"P",
    "gn:feature_code":"PPLA2",
    "gn:name":"Shiree",
    "gn:population":0,
    "gn:timezone":"Asia/Hovd",
    "iso:country":"MN",
    "name:und_x_variant":[
        "Tsagaan hayrhan sumu",
        "Tsagan Hayrhan",
        "Tsagan Khayrkhan somon",
        "Tsagaan Hayrhan Suma",
        "Tsagaanhayrhan",
        "Tsagaankha\u00efrkhan",
        "Tsagan-Khayrkhan"
    ],
    "wof:name":"Shiree",
    "wof:placetype":"locality"
},
  "geometry": {"coordinates":[96.80311,47.49714],"type":"Point"}
}