{
  "type": "Feature",
  "properties": {
    "gn:admin1_code":"01",
    "gn:asciiname":"Khuneyn sume",
    "gn:country_code":"MN",
    "gn:dem":1517,
    "gn:feature_class":"P",
    "gn:feature_code":"PPL",
    "gn:name":"Khuneyn sume",
    "gn:population":0,
    "gn:timezone":"Asia/Ulaanbaatar",
    "iso:country":"MN",
    "name:und_x_variant":[
        "H\u00fcny\u00fcn",
        "H\u00fcn\u00fcyn S\u00fcme"
    ],
    "wof:name":"Khuneyn sume",
    "wof:placetype":"locality"
},
  "geometry": {"coordinates":[101.62222,48.15861],"type":"Point"}
}