{
  "type": "Feature",
  "properties": {
    "gn:admin1_code":"13.0",
    "gn:asciiname":"Ibeeteyn Huryee",
    "gn:cc2":"MN",
    "gn:country_code":"MN",
    "gn:dem":1635,
    "gn:feature_class":"P",
    "gn:feature_code":"PPL",
    "gn:name":"Ibeeteyn H\u00fcryee",
    "gn:population":0,
    "gn:timezone":"Asia/Ulaanbaatar",
    "iso:country":"MN",
    "name:und_x_variant":[
        "Ibeteyn khure",
        "Ibeeteyn H\u00fcryee"
    ],
    "wof:name":"Ibeeteyn Huryee",
    "wof:placetype":"locality"
},
  "geometry": {"coordinates":[99.25,51.15],"type":"Point"}
}