{
  "type": "Feature",
  "properties": {
    "gn:admin1_code":"09",
    "gn:asciiname":"Asgat",
    "gn:country_code":"MN",
    "gn:dem":1702,
    "gn:feature_class":"P",
    "gn:feature_code":"PPLA2",
    "gn:name":"Asgat",
    "gn:population":0,
    "gn:timezone":"Asia/Hovd",
    "iso:country":"MN",
    "name:ceb_x_preferred":[
        "Asgat"
    ],
    "name:mon_x_preferred":[
        "Asgat"
    ],
    "name:mon_x_variant":[
        "\u0410\u0441\u0433\u0430\u0442 \u0441\u0443\u043c"
    ],
    "name:rus_x_preferred":[
        "\u0410\u0441\u0433\u0430\u0442"
    ],
    "name:swe_x_preferred":[
        "Asgat"
    ],
    "wof:name":"Asgat",
    "wof:placetype":"locality"
},
  "geometry": {"coordinates":[96.79944,49.51082],"type":"Point"}
}