{
  "type": "Feature",
  "properties": {
    "gn:admin1_code":"10.0",
    "gn:asciiname":"Buren",
    "gn:cc2":"MN",
    "gn:country_code":"MN",
    "gn:dem":1472,
    "gn:feature_class":"P",
    "gn:feature_code":"PPL",
    "gn:name":"B\u00fcren",
    "gn:population":0,
    "gn:timezone":"Asia/Hovd",
    "iso:country":"MN",
    "name:und_x_variant":[
        "B\u00fcran",
        "B\u00fcren"
    ],
    "wof:name":"Buren",
    "wof:placetype":"locality"
},
  "geometry": {"coordinates":[95.93333,47.26667],"type":"Point"}
}