{
  "type": "Feature",
  "properties": {
    "gn:admin1_code":"1.0",
    "gn:asciiname":"Tushaalta Hiid",
    "gn:cc2":"MN",
    "gn:country_code":"MN",
    "gn:dem":2122,
    "gn:feature_class":"P",
    "gn:feature_code":"PPL",
    "gn:name":"Tushaalta Hiid",
    "gn:population":0,
    "gn:timezone":"Asia/Ulaanbaatar",
    "iso:country":"MN",
    "name:und_x_variant":[
        "Kumirnya Tusukhaley",
        "Tusukhalei",
        "Tusuklalei",
        "Tuskhaltu Khid",
        "T\u2019u-su-ha-lieh Miao",
        "Tushaalta Hiid"
    ],
    "wof:name":"Tushaalta Hiid",
    "wof:placetype":"locality"
},
  "geometry": {"coordinates":[101.03333000000001,47.06667],"type":"Point"}
}