{
  "type": "Feature",
  "properties": {
    "gn:admin1_code":"6.0",
    "gn:asciiname":"Tugiin Sume",
    "gn:cc2":"MN",
    "gn:country_code":"MN",
    "gn:dem":835,
    "gn:feature_class":"P",
    "gn:feature_code":"PPL",
    "gn:name":"Tugiin S\u00fcme",
    "gn:population":0,
    "gn:timezone":"Asia/Choibalsan",
    "iso:country":"MN",
    "name:und_x_variant":[
        "Kumirnya Tuk-Sume",
        "Tug Sume",
        "Tuku-sume",
        "Tugin-Sume",
        "Tugiin S\u00fcme"
    ],
    "wof:name":"Tugiin Sume",
    "wof:placetype":"locality"
},
  "geometry": {"coordinates":[113.41667,47.98333],"type":"Point"}
}