{
  "type": "Feature",
  "properties": {
    "gn:admin1_code":"08",
    "gn:asciiname":"Hushuu Hiid",
    "gn:cc2":"MN",
    "gn:country_code":"MN",
    "gn:dem":1220,
    "gn:feature_class":"P",
    "gn:feature_code":"PPL",
    "gn:name":"Hushuu Hiid",
    "gn:population":0,
    "gn:timezone":"Asia/Ulaanbaatar",
    "iso:country":"MN",
    "name:und_x_variant":[
        "Khushu khid",
        "Hushuu-Hiyd",
        "Khoshu-Khid",
        "Ho-shun Hei-t\u2019e",
        "Kumirnya Khoshun-Khit",
        "Hoshun-hito",
        "Khoshu Khit",
        "Hushuu Hiid"
    ],
    "wof:name":"Hushuu Hiid",
    "wof:placetype":"locality"
},
  "geometry": {"coordinates":[104.11667,45.16667],"type":"Point"}
}