{
  "type": "Feature",
  "properties": {
    "gn:admin1_code":"11",
    "gn:asciiname":"Idermeg",
    "gn:cc2":"MN",
    "gn:country_code":"MN",
    "gn:dem":980,
    "gn:feature_class":"P",
    "gn:feature_code":"PPL",
    "gn:name":"Idermeg",
    "gn:population":0,
    "gn:timezone":"Asia/Ulaanbaatar",
    "iso:country":"MN",
    "name:und_x_variant":[
        "Idermeg Somon",
        "Idermeg Suma",
        "Idermeg Sumu",
        "Idermeg"
    ],
    "wof:name":"Idermeg",
    "wof:placetype":"locality"
},
  "geometry": {"coordinates":[111.33333,47.56667],"type":"Point"}
}