{
  "type": "Feature",
  "properties": {
    "gn:admin1_code":"8.0",
    "gn:asciiname":"Tsagaan-Ovoo",
    "gn:cc2":"MN",
    "gn:country_code":"MN",
    "gn:dem":1386,
    "gn:feature_class":"P",
    "gn:feature_code":"PPL",
    "gn:name":"Tsagaan-Ovoo",
    "gn:population":0,
    "gn:timezone":"Asia/Ulaanbaatar",
    "iso:country":"MN",
    "name:ceb_x_preferred":[
        "Tsagaan-Ovoo Sum"
    ],
    "name:mkd_x_preferred":[
        "\u0426\u0430\u0433\u0430\u043d-\u041e\u0432\u043e"
    ],
    "name:mon_x_preferred":[
        "\u0426\u0430\u0433\u0430\u0430\u043d-\u041e\u0432\u043e\u043e \u0441\u0443\u043c"
    ],
    "name:rus_x_preferred":[
        "\u0426\u0430\u0433\u0430\u0430\u043d-\u041e\u0432\u043e\u043e"
    ],
    "name:ukr_x_preferred":[
        "\u0426\u0430\u0433\u0430\u0430\u043d \u043e\u0432\u043e\u043e"
    ],
    "name:und_x_variant":[
        "Tsagaan oboo",
        "Tsagaan Oboonii Suma",
        "Tsagaan Oboonii",
        "Tsagaan oboo sumu",
        "Tsagaan-Owoo",
        "Tsagan Oboni Somon",
        "Tsagan-Oboni-Sumu",
        "Tsagaan-Ovoo"
    ],
    "wof:name":"Tsagaan-Ovoo",
    "wof:placetype":"locality"
},
  "geometry": {"coordinates":[105.23333,45.78333],"type":"Point"}
}