{
  "type": "Feature",
  "properties": {
    "gn:admin1_code":"07",
    "gn:asciiname":"Hashaata Hiid",
    "gn:country_code":"MN",
    "gn:dem":1081,
    "gn:feature_class":"P",
    "gn:feature_code":"PPL",
    "gn:name":"Hashaata Hiid",
    "gn:population":0,
    "gn:timezone":"Asia/Ulaanbaatar",
    "iso:country":"MN",
    "name:und_x_variant":[
        "Khashatu Khid",
        "Hashaata Hiid"
    ],
    "wof:name":"Hashaata Hiid",
    "wof:placetype":"locality"
},
  "geometry": {"coordinates":[108.90000000000001,43.26667],"type":"Point"}
}