{
  "type": "Feature",
  "properties": {
    "gn:admin1_code":"11",
    "gn:asciiname":"Boro Ondoriin Hiid",
    "gn:cc2":"MN",
    "gn:country_code":"MN",
    "gn:dem":1453,
    "gn:feature_class":"P",
    "gn:feature_code":"PPL",
    "gn:name":"Boro \u00d6nd\u00f6riin Hiid",
    "gn:population":0,
    "gn:timezone":"Asia/Ulaanbaatar",
    "iso:country":"MN",
    "name:und_x_variant":[
        "Koro Undur\u00f6yn Khid",
        "Boro-unduryyn-khid",
        "Boro Undur\u00f6yn Khid",
        "Boro \u00d6nd\u00f6riin Hiid"
    ],
    "wof:name":"Boro Ondoriin Hiid",
    "wof:placetype":"locality"
},
  "geometry": {"coordinates":[109.08333,47.66667],"type":"Point"}
}