{
  "type": "Feature",
  "properties": {
    "gn:admin1_code":"12.0",
    "gn:asciiname":"Togorigiin Sume",
    "gn:cc2":"MN",
    "gn:country_code":"MN",
    "gn:dem":1384,
    "gn:feature_class":"P",
    "gn:feature_code":"PPL",
    "gn:name":"T\u00f6g\u00f6rigiin S\u00fcme",
    "gn:population":0,
    "gn:timezone":"Asia/Hovd",
    "iso:country":"MN",
    "name:und_x_variant":[
        "Tugurigin Khure",
        "Tugurikin Sume",
        "T\u00f6g\u00f6rigiinhurie",
        "Tugurig\u2019iin h\u00fcrie",
        "T\u2019u-kou-liu-k\u2019o-yin",
        "Tugyuryuk-In",
        "T\u00f6g\u00f6rigiin S\u00fcme"
    ],
    "wof:name":"Togorigiin Sume",
    "wof:placetype":"locality"
},
  "geometry": {"coordinates":[92.16667,47.41667],"type":"Point"}
}