{
  "type": "Feature",
  "properties": {
    "gn:admin1_code":"2.0",
    "gn:asciiname":"Delgermoron",
    "gn:cc2":"MN",
    "gn:country_code":"MN",
    "gn:dem":2075,
    "gn:feature_class":"P",
    "gn:feature_code":"PPLA2",
    "gn:name":"Delgerm\u00f6r\u00f6n",
    "gn:population":0,
    "gn:timezone":"Asia/Ulaanbaatar",
    "iso:country":"MN",
    "name:ceb_x_preferred":[
        "H\u00fcreemaral"
    ],
    "name:mkd_x_preferred":[
        "\u0425\u0443\u0440\u0435\u043c\u0430\u0440\u0430\u043b"
    ],
    "name:mon_x_preferred":[
        "\u0425\u04af\u0440\u044d\u044d\u043c\u0430\u0440\u0430\u043b \u0441\u0443\u043c"
    ],
    "name:rus_x_preferred":[
        "\u0425\u0443\u0440\u044d\u044d\u043c\u0430\u0440\u0430\u043b"
    ],
    "name:swe_x_preferred":[
        "H\u00fcreemaral"
    ],
    "name:ukr_x_preferred":[
        "\u0425\u0443\u0440\u0435\u0435\u043c\u0430\u0440\u0430\u043b"
    ],
    "name:und_x_variant":[
        "Kh\u00fcreemaral",
        "Hureemaral"
    ],
    "wof:name":"Delgermoron",
    "wof:placetype":"locality"
},
  "geometry": {"coordinates":[98.28712,46.40946],"type":"Point"}
}