{
  "type": "Feature",
  "properties": {
    "gn:admin1_code":"2.0",
    "gn:asciiname":"Delgermoron",
    "gn:cc2":"MN",
    "gn:country_code":"MN",
    "gn:dem":2075,
    "gn:feature_class":"P",
    "gn:feature_code":"PPLA2",
    "gn:name":"Delgerm\u00f6r\u00f6n",
    "gn:population":0,
    "gn:timezone":"Asia/Ulaanbaatar",
    "iso:country":"MN",
    "name:und_x_variant":[
        "Kh\u00fcreemaral",
        "Hureemaral"
    ],
    "wof:name":"Delgermoron",
    "wof:placetype":"locality"
},
  "geometry": {"coordinates":[98.28712,46.40946],"type":"Point"}
}