{
  "type": "Feature",
  "properties": {
    "gn:admin1_code":"06",
    "gn:asciiname":"Han-Uul",
    "gn:cc2":"MN",
    "gn:country_code":"MN",
    "gn:dem":752,
    "gn:feature_class":"P",
    "gn:feature_code":"PPL",
    "gn:name":"Han-Uul",
    "gn:population":0,
    "gn:timezone":"Asia/Choibalsan",
    "iso:country":"MN",
    "name:und_x_variant":[
        "Khan-Uul",
        "Han-Uul"
    ],
    "wof:name":"Han-Uul",
    "wof:placetype":"locality"
},
  "geometry": {"coordinates":[114.66667,48.01667],"type":"Point"}
}