{
  "type": "Feature",
  "properties": {
    "gn:admin1_code":"11",
    "gn:asciiname":"Gashuunii Hiid",
    "gn:cc2":"MN",
    "gn:country_code":"MN",
    "gn:dem":1103,
    "gn:feature_class":"P",
    "gn:feature_code":"PPL",
    "gn:name":"Gashuunii Hiid",
    "gn:population":0,
    "gn:timezone":"Asia/Ulaanbaatar",
    "iso:country":"MN",
    "name:und_x_variant":[
        "Gashuny Khid",
        "Gashunyy-khid",
        "Gashuunii Hiid"
    ],
    "wof:name":"Gashuunii Hiid",
    "wof:placetype":"locality"
},
  "geometry": {"coordinates":[112.31667,48.26667],"type":"Point"}
}