{
  "type": "Feature",
  "properties": {
    "gn:admin1_code":"01",
    "gn:asciiname":"Aygatayn Dugang",
    "gn:cc2":"MN",
    "gn:country_code":"MN",
    "gn:dem":1528,
    "gn:feature_class":"P",
    "gn:feature_code":"PPL",
    "gn:name":"Aygatayn Dugang",
    "gn:population":0,
    "gn:timezone":"Asia/Ulaanbaatar",
    "iso:country":"MN",
    "name:und_x_variant":[
        "Aygatuin dugang",
        "Aygatayn Dugang"
    ],
    "wof:name":"Aygatayn Dugang",
    "wof:placetype":"locality"
},
  "geometry": {"coordinates":[101.05,49.01667],"type":"Point"}
}