{
  "type": "Feature",
  "properties": {
    "gn:admin1_code":"8.0",
    "gn:asciiname":"Uula Hural",
    "gn:cc2":"MN",
    "gn:country_code":"MN",
    "gn:dem":1151,
    "gn:feature_class":"P",
    "gn:feature_code":"PPL",
    "gn:name":"Uula Hural",
    "gn:population":0,
    "gn:timezone":"Asia/Ulaanbaatar",
    "iso:country":"MN",
    "name:und_x_variant":[
        "Uli khural",
        "Ula-Khora",
        "Ula Khural",
        "Uula Hural"
    ],
    "wof:name":"Uula Hural",
    "wof:placetype":"locality"
},
  "geometry": {"coordinates":[107.68333,45.56667],"type":"Point"}
}