{
  "type": "Feature",
  "properties": {
    "gn:admin1_code":"16",
    "gn:asciiname":"Bayan Goliin Den",
    "gn:cc2":"MN",
    "gn:country_code":"MN",
    "gn:dem":840,
    "gn:feature_class":"P",
    "gn:feature_code":"PPL",
    "gn:name":"Bayan Goliin Den",
    "gn:population":0,
    "gn:timezone":"Asia/Ulaanbaatar",
    "iso:country":"MN",
    "name:und_x_variant":[
        "Stanok Bayan-Golyyn-Dyan",
        "Bayan Goliin Den"
    ],
    "wof:name":"Bayan Goliin Den",
    "wof:placetype":"locality"
},
  "geometry": {"coordinates":[106.11667,49.03333],"type":"Point"}
}