{
  "type": "Feature",
  "properties": {
    "gn:admin1_code":"18",
    "gn:asciiname":"Ara Bulagiin Dugang",
    "gn:cc2":"MN",
    "gn:country_code":"MN",
    "gn:dem":1122,
    "gn:feature_class":"P",
    "gn:feature_code":"PPL",
    "gn:name":"Ara Bulagiin Dugang",
    "gn:population":0,
    "gn:timezone":"Asia/Ulaanbaatar",
    "iso:country":"MN",
    "name:und_x_variant":[
        "Ara-bulagyyn dugang",
        "Ara Bulagiin Dugang"
    ],
    "wof:name":"Ara Bulagiin Dugang",
    "wof:placetype":"locality"
},
  "geometry": {"coordinates":[105.59999999999999,48.43333],"type":"Point"}
}