{
  "type": "Feature",
  "properties": {
    "gn:admin1_code":"18",
    "gn:asciiname":"Nueuerst",
    "gn:country_code":"MN",
    "gn:dem":1355,
    "gn:feature_class":"P",
    "gn:feature_code":"PPL",
    "gn:name":"N\u00fc\u00fcrst",
    "gn:population":0,
    "gn:timezone":"Asia/Ulaanbaatar",
    "iso:country":"MN",
    "wof:name":"Nueuerst",
    "wof:placetype":"locality"
},
  "geometry": {"coordinates":[108.36502,47.75456],"type":"Point"}
}