{
  "type": "Feature",
  "properties": {
    "gn:admin1_code":"6.0",
    "gn:asciiname":"Ubur Urtyyn Urto",
    "gn:country_code":"MN",
    "gn:dem":980,
    "gn:feature_class":"P",
    "gn:feature_code":"PPL",
    "gn:name":"Ubur Urtyyn Urto",
    "gn:population":0,
    "gn:timezone":"Asia/Choibalsan",
    "iso:country":"MN",
    "name:und_x_variant":[
        "Ubur Urt\u00f6yn Urto",
        "Ubur-Urtyyn",
        "Ubur urtiyn urto",
        "Ubur Urtyyn Urto",
        "\u00d6b\u00f6r Urtaiin \u00d6rt\u00f6\u00f6"
    ],
    "wof:name":"Ubur Urtyyn Urto",
    "wof:placetype":"locality"
},
  "geometry": {"coordinates":[114.08333,47.58333],"type":"Point"}
}