{
  "type": "Feature",
  "properties": {
    "gn:admin1_code":"06",
    "gn:asciiname":"Halhgol",
    "gn:country_code":"MN",
    "gn:dem":602,
    "gn:feature_class":"P",
    "gn:feature_code":"PPL",
    "gn:name":"Halhgol",
    "gn:population":0,
    "gn:timezone":"Asia/Choibalsan",
    "iso:country":"MN",
    "wof:name":"Halhgol",
    "wof:placetype":"locality"
},
  "geometry": {"coordinates":[118.08333,47.93333],"type":"Point"}
}