{
  "type": "Feature",
  "properties": {
    "gn:admin1_code":"20.0",
    "gn:asciiname":"Shadablingi Hiid",
    "gn:cc2":"MN",
    "gn:country_code":"MN",
    "gn:dem":1527,
    "gn:feature_class":"P",
    "gn:feature_code":"PPL",
    "gn:name":"Shadablingi Hiid",
    "gn:population":0,
    "gn:timezone":"Asia/Ulaanbaatar",
    "iso:country":"MN",
    "name:und_x_variant":[
        "Shadablingi-Khid",
        "Shaddbling Khid",
        "Shadablingi Hiid"
    ],
    "wof:name":"Shadablingi Hiid",
    "wof:placetype":"locality"
},
  "geometry": {"coordinates":[106.90000000000001,48.01667],"type":"Point"}
}