{
  "type": "Feature",
  "properties": {
    "gn:admin1_code":"07",
    "gn:asciiname":"Buuteriin Hural",
    "gn:cc2":"MN",
    "gn:country_code":"MN",
    "gn:dem":1000,
    "gn:feature_class":"P",
    "gn:feature_code":"PPL",
    "gn:name":"B\u00fc\u00fcteriin Hural",
    "gn:population":0,
    "gn:timezone":"Asia/Ulaanbaatar",
    "iso:country":"MN",
    "name:und_x_variant":[
        "Buterin Khural",
        "B\u00fc\u00fcteriin Hural"
    ],
    "wof:name":"Buuteriin Hural",
    "wof:placetype":"locality"
},
  "geometry": {"coordinates":[109.41667,45.48333],"type":"Point"}
}