{
  "type": "Feature",
  "properties": {
    "gn:admin1_code":"10.0",
    "gn:asciiname":"Togorigiin Huryee",
    "gn:cc2":"MN",
    "gn:country_code":"MN",
    "gn:dem":2342,
    "gn:feature_class":"P",
    "gn:feature_code":"PPL",
    "gn:name":"T\u00f6g\u00f6rigiin H\u00fcryee",
    "gn:population":0,
    "gn:timezone":"Asia/Hovd",
    "iso:country":"MN",
    "name:und_x_variant":[
        "Tugurigiin Khure",
        "T\u00f6g\u00f6rigiin H\u00fcryee"
    ],
    "wof:name":"Togorigiin Huryee",
    "wof:placetype":"locality"
},
  "geometry": {"coordinates":[96.66667,45.33333],"type":"Point"}
}