{
  "type": "Feature",
  "properties": {
    "gn:admin1_code":"18",
    "gn:asciiname":"Javhlant",
    "gn:cc2":"MN",
    "gn:country_code":"MN",
    "gn:dem":864,
    "gn:feature_class":"P",
    "gn:feature_code":"PPLA2",
    "gn:name":"Javhlant",
    "gn:population":0,
    "gn:timezone":"Asia/Ulaanbaatar",
    "iso:country":"MN",
    "name:und_x_variant":[
        "S\u00fcmber"
    ],
    "wof:name":"Javhlant",
    "wof:placetype":"locality"
},
  "geometry": {"coordinates":[105.92400000000001,48.80189],"type":"Point"}
}