{
  "type": "Feature",
  "properties": {
    "gn:admin1_code":"18.0",
    "gn:asciiname":"Tomor Usatanii Panja",
    "gn:cc2":"MN",
    "gn:country_code":"MN",
    "gn:dem":1516,
    "gn:feature_class":"P",
    "gn:feature_code":"PPL",
    "gn:name":"T\u00f6m\u00f6r Usatanii Panja",
    "gn:population":0,
    "gn:timezone":"Asia/Ulaanbaatar",
    "iso:country":"MN",
    "name:und_x_variant":[
        "Tumur-usatunyy-panchzha",
        "Tumur Usatunoy Panchzha",
        "T\u00f6m\u00f6r Usatanii Panja"
    ],
    "wof:name":"Tomor Usatanii Panja",
    "wof:placetype":"locality"
},
  "geometry": {"coordinates":[108.33333,47.25],"type":"Point"}
}