{
  "type": "Feature",
  "properties": {
    "gn:admin1_code":"02",
    "gn:asciiname":"Hohburd",
    "gn:cc2":"MN",
    "gn:country_code":"MN",
    "gn:dem":1951,
    "gn:feature_class":"P",
    "gn:feature_code":"PPLA2",
    "gn:name":"H\u00f6hb\u00fcrd",
    "gn:population":0,
    "gn:timezone":"Asia/Ulaanbaatar",
    "iso:country":"MN",
    "name:und_x_variant":[
        "Bayan-Owoo",
        "Bayan-Ovoo"
    ],
    "wof:name":"Hohburd",
    "wof:placetype":"locality"
},
  "geometry": {"coordinates":[100.44834,46.28575],"type":"Point"}
}