{
  "type": "Feature",
  "properties": {
    "gn:admin1_code":"08",
    "gn:asciiname":"Enger Dzulagtayn Hural",
    "gn:cc2":"MN",
    "gn:country_code":"MN",
    "gn:dem":1399,
    "gn:feature_class":"P",
    "gn:feature_code":"PPL",
    "gn:name":"Enger Dzulagtayn Hural",
    "gn:population":0,
    "gn:timezone":"Asia/Ulaanbaatar",
    "iso:country":"MN",
    "name:und_x_variant":[
        "Enger Tszulugtuin Khural",
        "Enger Tszulugtuyn Khural",
        "Enger Dzulagtayn Hural"
    ],
    "wof:name":"Enger Dzulagtayn Hural",
    "wof:placetype":"locality"
},
  "geometry": {"coordinates":[107.43333,45.96667],"type":"Point"}
}