{
  "type": "Feature",
  "properties": {
    "gn:admin1_code":"11",
    "gn:asciiname":"Gurban Bayan Suma",
    "gn:cc2":"MN",
    "gn:country_code":"MN",
    "gn:dem":1114,
    "gn:feature_class":"P",
    "gn:feature_code":"PPL",
    "gn:name":"Gurban Bayan Suma",
    "gn:population":0,
    "gn:timezone":"Asia/Ulaanbaatar",
    "iso:country":"MN",
    "name:und_x_variant":[
        "Gurban-Bayan-Somon",
        "Gurban-Bayan",
        "Gurbun-Bayan-Somon",
        "Gurban Bayan Sum",
        "Gurban Bayan Suma"
    ],
    "wof:name":"Gurban Bayan Suma",
    "wof:placetype":"locality"
},
  "geometry": {"coordinates":[112.25,48.43333],"type":"Point"}
}