{
  "type": "Feature",
  "properties": {
    "gn:admin1_code":"9.0",
    "gn:asciiname":"Goliin Huryee",
    "gn:cc2":"MN",
    "gn:country_code":"MN",
    "gn:dem":2365,
    "gn:feature_class":"P",
    "gn:feature_code":"PPL",
    "gn:name":"Goliin H\u00fcryee",
    "gn:population":0,
    "gn:timezone":"Asia/Hovd",
    "iso:country":"MN",
    "name:und_x_variant":[
        "Goliin Khure",
        "Goliin H\u00fcryee"
    ],
    "wof:name":"Goliin Huryee",
    "wof:placetype":"locality"
},
  "geometry": {"coordinates":[97.71666999999999,47.45],"type":"Point"}
}