{
  "type": "Feature",
  "properties": {
    "gn:admin1_code":"16.0",
    "gn:asciiname":"Uylgaiin Dugang",
    "gn:cc2":"MN",
    "gn:country_code":"MN",
    "gn:dem":767,
    "gn:feature_class":"P",
    "gn:feature_code":"PPL",
    "gn:name":"Uylgaiin Dugang",
    "gn:population":0,
    "gn:timezone":"Asia/Ulaanbaatar",
    "iso:country":"MN",
    "name:und_x_variant":[
        "Uilgain dugang",
        "Uilgan dugang",
        "Uilgiin Dugan",
        "Ulygaiin-Dugan",
        "Uylgaiin Dugang"
    ],
    "wof:name":"Uylgaiin Dugang",
    "wof:placetype":"locality"
},
  "geometry": {"coordinates":[107.73333,49.81667],"type":"Point"}
}