{
  "type": "Feature",
  "properties": {
    "gn:admin1_code":"9.0",
    "gn:asciiname":"Telmin Suma",
    "gn:country_code":"MN",
    "gn:dem":1794,
    "gn:feature_class":"P",
    "gn:feature_code":"PPLA2",
    "gn:name":"Telmin Suma",
    "gn:population":0,
    "gn:timezone":"Asia/Hovd",
    "iso:country":"MN",
    "name:ceb_x_preferred":[
        "Telmen"
    ],
    "name:eng_x_preferred":[
        "\u00d6v\u00f6gdiy"
    ],
    "name:mkd_x_preferred":[
        "\u0422\u0435\u043b\u043c\u0435\u043d"
    ],
    "name:mon_x_preferred":[
        "\u00d6v\u00f6gdiy"
    ],
    "name:mon_x_variant":[
        "\u0422\u044d\u043b\u043c\u044d\u043d \u0441\u0443\u043c"
    ],
    "name:rus_x_preferred":[
        "\u0422\u044d\u043b\u043c\u044d\u043d"
    ],
    "name:ukr_x_preferred":[
        "\u0422\u0435\u043b\u043c\u0435\u043d"
    ],
    "name:und_x_variant":[
        "Tel\u2019min sumu",
        "Telmin",
        "\u00d6vg\u00f6diy",
        "Telmin somon",
        "Telmen"
    ],
    "wof:name":"Telmin Suma",
    "wof:placetype":"locality"
},
  "geometry": {"coordinates":[97.61861,48.64278],"type":"Point"}
}