{
  "type": "Feature",
  "properties": {
    "gn:admin1_code":"18.0",
    "gn:asciiname":"Ugumur",
    "gn:country_code":"MN",
    "gn:dem":1358,
    "gn:feature_class":"P",
    "gn:feature_code":"PPL",
    "gn:name":"Ugumur",
    "gn:population":0,
    "gn:timezone":"Asia/Ulaanbaatar",
    "iso:country":"MN",
    "name:und_x_variant":[
        "Okomur",
        "\u00d6g\u00f6\u00f6m\u00f6r"
    ],
    "wof:name":"Ugumur",
    "wof:placetype":"locality"
},
  "geometry": {"coordinates":[107.98333,46.98333],"type":"Point"}
}