{
  "type": "Feature",
  "properties": {
    "gn:admin1_code":"11",
    "gn:asciiname":"Buyant",
    "gn:country_code":"MN",
    "gn:dem":1191,
    "gn:feature_class":"P",
    "gn:feature_code":"PPLA2",
    "gn:name":"Buyant",
    "gn:population":0,
    "gn:timezone":"Asia/Ulaanbaatar",
    "iso:country":"MN",
    "name:ceb_x_preferred":[
        "Buyant"
    ],
    "name:mon_x_preferred":[
        "Buyant"
    ],
    "name:mon_x_variant":[
        "\u0411\u0443\u044f\u043d\u0442 \u0441\u0443\u043c"
    ],
    "name:swe_x_preferred":[
        "Buyant"
    ],
    "name:und_x_variant":[
        "Boendosumu",
        "Buyantyin-Somon",
        "Buyantyyn somon",
        "Buyantyn-Somon",
        "Buyanta Suma",
        "Buyantu sumu",
        "Buyant\u00f6n Somon",
        "Buyantu Sume",
        "Buyantu",
        "Buyant\u00f6yn-Somon"
    ],
    "wof:name":"Buyant",
    "wof:placetype":"locality"
},
  "geometry": {"coordinates":[110.83333,46.25],"type":"Point"}
}