{
  "type": "Feature",
  "properties": {
    "gn:admin1_code":"07",
    "gn:asciiname":"Hutag-Uul",
    "gn:cc2":"MN",
    "gn:country_code":"MN",
    "gn:dem":1127,
    "gn:feature_class":"P",
    "gn:feature_code":"PPL",
    "gn:name":"Hutag-Uul",
    "gn:population":0,
    "gn:timezone":"Asia/Ulaanbaatar",
    "iso:country":"MN",
    "name:und_x_variant":[
        "Khutag-Uul",
        "Hutag-Uul"
    ],
    "wof:name":"Hutag-Uul",
    "wof:placetype":"locality"
},
  "geometry": {"coordinates":[110.21472,43.35167],"type":"Point"}
}