{
  "type": "Feature",
  "properties": {
    "gn:admin1_code":"18",
    "gn:asciiname":"Arhust",
    "gn:cc2":"MN",
    "gn:country_code":"MN",
    "gn:dem":1569,
    "gn:feature_class":"P",
    "gn:feature_code":"PPLA2",
    "gn:name":"Arhust",
    "gn:population":0,
    "gn:timezone":"Asia/Ulaanbaatar",
    "iso:country":"MN",
    "name:und_x_variant":[
        "Erdene",
        "Erdeni Sumny Horshoo"
    ],
    "wof:name":"Arhust",
    "wof:placetype":"locality"
},
  "geometry": {"coordinates":[107.88334,47.79425],"type":"Point"}
}