{
  "type": "Feature",
  "properties": {
    "gn:admin1_code":"18",
    "gn:asciiname":"Bayan Baraatayn Hiid",
    "gn:cc2":"MN",
    "gn:country_code":"MN",
    "gn:dem":1411,
    "gn:feature_class":"P",
    "gn:feature_code":"PPL",
    "gn:name":"Bayan Baraatayn Hiid",
    "gn:population":0,
    "gn:timezone":"Asia/Ulaanbaatar",
    "iso:country":"MN",
    "name:und_x_variant":[
        "Bayan Baratuin Khid",
        "Bayan baratuyn khid",
        "Bayan Baraatayn Hiid"
    ],
    "wof:name":"Bayan Baraatayn Hiid",
    "wof:placetype":"locality"
},
  "geometry": {"coordinates":[106.48333,46.71667],"type":"Point"}
}