{
  "type": "Feature",
  "properties": {
    "gn:admin1_code":"11.0",
    "gn:asciiname":"Uhaa Hushuunii Hiid",
    "gn:cc2":"MN",
    "gn:country_code":"MN",
    "gn:dem":1013,
    "gn:feature_class":"P",
    "gn:feature_code":"PPL",
    "gn:name":"Uhaa Hushuunii Hiid",
    "gn:population":0,
    "gn:timezone":"Asia/Ulaanbaatar",
    "iso:country":"MN",
    "name:und_x_variant":[
        "Ukha-khushuny-khid",
        "Ukha-khushunyy khid",
        "Uhaa Hushuunii Hiid"
    ],
    "wof:name":"Uhaa Hushuunii Hiid",
    "wof:placetype":"locality"
},
  "geometry": {"coordinates":[111.98333,48.76667],"type":"Point"}
}