{
  "type": "Feature",
  "properties": {
    "gn:admin1_code":"21.0",
    "gn:asciiname":"Surte Dugang",
    "gn:country_code":"MN",
    "gn:dem":1145,
    "gn:feature_class":"P",
    "gn:feature_code":"PPL",
    "gn:name":"S\u00fcrte Dugang",
    "gn:population":0,
    "gn:timezone":"Asia/Ulaanbaatar",
    "iso:country":"MN",
    "wof:name":"Surte Dugang",
    "wof:placetype":"locality"
},
  "geometry": {"coordinates":[104.45,49.35],"type":"Point"}
}