{
  "type": "Feature",
  "properties": {
    "gn:admin1_code":"21.0",
    "gn:asciiname":"Tsoohoriin Hural",
    "gn:country_code":"MN",
    "gn:dem":1116,
    "gn:feature_class":"P",
    "gn:feature_code":"PPL",
    "gn:name":"Tsoohoriin Hural",
    "gn:population":0,
    "gn:timezone":"Asia/Ulaanbaatar",
    "iso:country":"MN",
    "name:und_x_variant":[
        "Tsakhirin Khural",
        "Tsokhoriin Khural",
        "Tsoohoriin Hural"
    ],
    "wof:name":"Tsoohoriin Hural",
    "wof:placetype":"locality"
},
  "geometry": {"coordinates":[104.41667,47.63333],"type":"Point"}
}