{
  "type": "Feature",
  "properties": {
    "gn:admin1_code":"21",
    "gn:asciiname":"Bayan Dugang",
    "gn:cc2":"MN",
    "gn:country_code":"MN",
    "gn:dem":1300,
    "gn:feature_class":"P",
    "gn:feature_code":"PPL",
    "gn:name":"Bayan Dugang",
    "gn:population":0,
    "gn:timezone":"Asia/Ulaanbaatar",
    "iso:country":"MN",
    "name:und_x_variant":[
        "Bayn Dugan",
        "Bayan-dugan",
        "Bain-dugan",
        "Bayan Dugang"
    ],
    "wof:name":"Bayan Dugang",
    "wof:placetype":"locality"
},
  "geometry": {"coordinates":[103.61667,49.51667],"type":"Point"}
}