{
  "type": "Feature",
  "properties": {
    "gn:admin1_code":"20",
    "gn:asciiname":"Engershand",
    "gn:cc2":"MN",
    "gn:country_code":"MN",
    "gn:dem":1427,
    "gn:feature_class":"P",
    "gn:feature_code":"PPL",
    "gn:name":"Engershand",
    "gn:population":0,
    "gn:timezone":"Asia/Ulaanbaatar",
    "iso:country":"MN",
    "name:und_x_variant":[
        "Bayan-Tszuri-Somon",
        "Bayan dz\u00fcrihe",
        "Bayan Djurkhe Sume",
        "Bayan dz\u00fcrihe sumu",
        "Bayandz\u00fcrh",
        "Bayan Tszurikhe Somon",
        "Bayan Dz\u00fcrihe Suma",
        "Bayan-Dzhirukhe-Sumu",
        "Engershand"
    ],
    "wof:name":"Engershand",
    "wof:placetype":"locality"
},
  "geometry": {"coordinates":[107.16667,47.81667],"type":"Point"}
}