{
  "type": "Feature",
  "properties": {
    "gn:admin1_code":"17",
    "gn:asciiname":"Haylaastay",
    "gn:country_code":"MN",
    "gn:dem":898,
    "gn:feature_class":"P",
    "gn:feature_code":"PPLA2",
    "gn:name":"Haylaastay",
    "gn:population":0,
    "gn:timezone":"Asia/Choibalsan",
    "iso:country":"MN",
    "name:mon_x_preferred":[
        "Haylaastay"
    ],
    "name:mon_x_variant":[
        "\u0425\u0430\u0439\u043b\u0430\u0430\u0441\u0442\u0430\u0439",
        "\u0421\u04af\u0445\u0431\u0430\u0430\u0442\u0430\u0440"
    ],
    "name:und_x_variant":[
        "Sukhe Batur",
        "Sukhe-Bator",
        "Sakhe Bataar",
        "S\u00fchbaatar",
        "S\u00fckhbaatar"
    ],
    "wof:name":"Haylaastay",
    "wof:placetype":"locality"
},
  "geometry": {"coordinates":[113.88248,46.77076],"type":"Point"}
}