{
  "type": "Feature",
  "properties": {
    "gn:admin1_code":"18",
    "gn:asciiname":"Bagshiin Hiid",
    "gn:cc2":"MN",
    "gn:country_code":"MN",
    "gn:dem":1586,
    "gn:feature_class":"P",
    "gn:feature_code":"PPL",
    "gn:name":"Bagshiin Hiid",
    "gn:population":0,
    "gn:timezone":"Asia/Ulaanbaatar",
    "iso:country":"MN",
    "name:und_x_variant":[
        "Bagshiin-Hiyd",
        "Bagshiin Khid",
        "Bagshiin Hiid"
    ],
    "wof:name":"Bagshiin Hiid",
    "wof:placetype":"locality"
},
  "geometry": {"coordinates":[106.98333,47.73333],"type":"Point"}
}