{
  "type": "Feature",
  "properties": {
    "gn:admin1_code":"17",
    "gn:asciiname":"Dzuunbulag",
    "gn:country_code":"MN",
    "gn:dem":1020,
    "gn:feature_class":"P",
    "gn:feature_code":"PPLA2",
    "gn:name":"Dz\u00fc\u00fcnbulag",
    "gn:population":0,
    "gn:timezone":"Asia/Choibalsan",
    "iso:country":"MN",
    "name:mon_x_preferred":[
        "Dz\u00fc\u00fcnbulag"
    ],
    "name:und_x_variant":[
        "Ul\u2019-bain-munku Somon",
        "Uulbayan M\u00f6nh",
        "Ul\u2019bayn Munku Somon",
        "Uula Bayan M\u00f6nh\u00f6 Suma",
        "Uula bayan m\u00f6nh\u00f6",
        "Ula bayan m\u00f6nh\u00f6 Sumu",
        "Uulbayan",
        "Ula-Bayan-Munkhu"
    ],
    "wof:name":"Dzuunbulag",
    "wof:placetype":"locality"
},
  "geometry": {"coordinates":[112.18333,46.38333],"type":"Point"}
}