{
  "type": "Feature",
  "properties": {
    "gn:admin1_code":"23",
    "gn:asciiname":"Hongor",
    "gn:country_code":"MN",
    "gn:dem":747,
    "gn:feature_class":"P",
    "gn:feature_code":"PPLA2",
    "gn:name":"Hongor",
    "gn:population":0,
    "gn:timezone":"Asia/Ulaanbaatar",
    "iso:country":"MN",
    "name:ceb_x_preferred":[
        "Hongor"
    ],
    "name:mon_x_preferred":[
        "Hongor"
    ],
    "name:mon_x_variant":[
        "\u0425\u043e\u043d\u0433\u043e\u0440"
    ],
    "name:swe_x_preferred":[
        "Hongor"
    ],
    "wof:name":"Hongor",
    "wof:placetype":"locality"
},
  "geometry": {"coordinates":[105.89673999999999,49.23012],"type":"Point"}
}