{
  "type": "Feature",
  "properties": {
    "gn:admin1_code":"3.0",
    "gn:asciiname":"Tsagaannuur",
    "gn:country_code":"MN",
    "gn:dem":2110,
    "gn:feature_class":"P",
    "gn:feature_code":"PPL",
    "gn:name":"Tsagaannuur",
    "gn:population":200,
    "gn:timezone":"Asia/Hovd",
    "iso:country":"MN",
    "name:eng_x_preferred":[
        "Tsagaannuur"
    ],
    "name:rus_x_preferred":[
        "\u0426\u0430\u0433\u0430\u043d-\u041d\u0443\u0440"
    ],
    "name:und_x_variant":[
        "Tsagan-nur"
    ],
    "wof:name":"Tsagaannuur",
    "wof:placetype":"locality",
    "wof:population":200
},
  "geometry": {"coordinates":[89.73289,49.50938],"type":"Point"}
}