{
  "type": "Feature",
  "properties": {
    "gn:admin1_code":"21",
    "gn:asciiname":"Haratayn Hural",
    "gn:cc2":"MN",
    "gn:country_code":"MN",
    "gn:dem":1184,
    "gn:feature_class":"P",
    "gn:feature_code":"PPL",
    "gn:name":"Haratayn Hural",
    "gn:population":0,
    "gn:timezone":"Asia/Ulaanbaatar",
    "iso:country":"MN",
    "name:und_x_variant":[
        "Kharatuin Khural",
        "Haratayn Hural"
    ],
    "wof:name":"Haratayn Hural",
    "wof:placetype":"locality"
},
  "geometry": {"coordinates":[103.45,47.88333],"type":"Point"}
}