{
  "type": "Feature",
  "properties": {
    "gn:admin1_code":"23",
    "gn:asciiname":"Orhon",
    "gn:country_code":"MN",
    "gn:dem":638,
    "gn:feature_class":"P",
    "gn:feature_code":"PPLA2",
    "gn:name":"Orhon",
    "gn:population":0,
    "gn:timezone":"Asia/Ulaanbaatar",
    "iso:country":"MN",
    "name:eng_x_preferred":[
        "Orhon"
    ],
    "name:mkd_x_preferred":[
        "\u041e\u0440\u0445\u043e\u043d"
    ],
    "name:mon_x_preferred":[
        "Orhon"
    ],
    "name:mon_x_variant":[
        "\u041e\u0440\u0445\u043e\u043d",
        "\u041e\u0440\u0445\u043e\u043d \u0441\u0443\u043c"
    ],
    "name:rus_x_preferred":[
        "\u041e\u0440\u0445\u043e\u043d"
    ],
    "name:und_x_variant":[
        "Harosha",
        "Orkhon"
    ],
    "wof:name":"Orhon",
    "wof:placetype":"locality"
},
  "geometry": {"coordinates":[106.13639000000001,49.8325],"type":"Point"}
}