{
  "type": "Feature",
  "properties": {
    "gn:admin1_code":"07",
    "gn:asciiname":"Deresenii Hural",
    "gn:cc2":"MN",
    "gn:country_code":"MN",
    "gn:dem":1072,
    "gn:feature_class":"P",
    "gn:feature_code":"PPL",
    "gn:name":"Deresenii Hural",
    "gn:population":0,
    "gn:timezone":"Asia/Ulaanbaatar",
    "iso:country":"MN",
    "name:und_x_variant":[
        "Deresunyy khural",
        "Deresun\u00f6y Khural",
        "Deresenii Hural"
    ],
    "wof:name":"Deresenii Hural",
    "wof:placetype":"locality"
},
  "geometry": {"coordinates":[109.78333000000001,43.78333],"type":"Point"}
}