{
  "type": "Feature",
  "properties": {
    "gn:admin1_code":"11.0",
    "gn:asciiname":"Tarihaiin Sume",
    "gn:cc2":"MN",
    "gn:country_code":"MN",
    "gn:dem":1352,
    "gn:feature_class":"P",
    "gn:feature_code":"PPL",
    "gn:name":"Tarihaiin S\u00fcme",
    "gn:population":0,
    "gn:timezone":"Asia/Ulaanbaatar",
    "iso:country":"MN",
    "name:und_x_variant":[
        "Tarih\u00efn",
        "Tarikhuin-Sume",
        "Tarihaiin S\u00fcme"
    ],
    "wof:name":"Tarihaiin Sume",
    "wof:placetype":"locality"
},
  "geometry": {"coordinates":[109.66667,48.48333],"type":"Point"}
}