{
  "type": "Feature",
  "properties": {
    "gn:admin1_code":"8.0",
    "gn:asciiname":"Tavan-Jisa",
    "gn:country_code":"MN",
    "gn:dem":1402,
    "gn:feature_class":"P",
    "gn:feature_code":"PPL",
    "gn:name":"Tavan-Jisa",
    "gn:population":0,
    "gn:timezone":"Asia/Ulaanbaatar",
    "iso:country":"MN",
    "wof:name":"Tavan-Jisa",
    "wof:placetype":"locality"
},
  "geometry": {"coordinates":[107.34999999999999,45.95],"type":"Point"}
}