{
  "type": "Feature",
  "properties": {
    "gn:admin1_code":"06",
    "gn:asciiname":"Erdeni Guunii Hiid",
    "gn:cc2":"MN",
    "gn:country_code":"MN",
    "gn:dem":979,
    "gn:feature_class":"P",
    "gn:feature_code":"PPL",
    "gn:name":"Erdeni Guunii Hiid",
    "gn:population":0,
    "gn:timezone":"Asia/Choibalsan",
    "iso:country":"MN",
    "name:und_x_variant":[
        "Erdeni G\u00fcnii Khiit",
        "Erdeni-guniy-khid",
        "Erdeni-Gunii-Khid",
        "Erdeni Guni Khid",
        "Erdeni Guunii Hiid"
    ],
    "wof:name":"Erdeni Guunii Hiid",
    "wof:placetype":"locality"
},
  "geometry": {"coordinates":[112.61667,48.36667],"type":"Point"}
}