{
  "type": "Feature",
  "properties": {
    "iso:country":"MN",
    "name:cat_x_preferred":[
        "Baiankhongor"
    ],
    "name:ces_x_preferred":[
        "Bajanchongor"
    ],
    "name:deu_x_preferred":[
        "Bajanchongor"
    ],
    "name:dsb_x_preferred":[
        "Bajanchongor"
    ],
    "name:fas_x_preferred":[
        "\u0628\u06cc\u0627\u0646\u062e\u0627\u0646\u06af\u0627\u0631"
    ],
    "name:fin_x_preferred":[
        "Bajanhongor"
    ],
    "name:fra_x_preferred":[
        "Bayanhongor"
    ],
    "name:heb_x_preferred":[
        "\u05d1\u05d0\u05d9\u05d9\u05e0\u05d7\u05d5\u05e0\u05d2\u05d5\u05e8"
    ],
    "name:hin_x_preferred":[
        "\u092c\u092f\u0928\u0916\u094b\u0902\u0917\u094b\u0930"
    ],
    "name:ita_x_preferred":[
        "Bajanhongor"
    ],
    "name:kat_x_preferred":[
        "\u10d1\u10d0\u10d8\u10d0\u10dc\u10ee\u10dd\u10dc\u10d2\u10dd\u10e0\u10d8"
    ],
    "name:kor_x_preferred":[
        "\ubc14\uc591\ud64d\uace0\ub974"
    ],
    "name:lit_x_preferred":[
        "Bajanchongoras"
    ],
    "name:mkd_x_preferred":[
        "\u0411\u0430\u0458\u0430\u043d\u0445\u043e\u043d\u0433\u043e\u0440"
    ],
    "name:mon_x_preferred":[
        "\u0411\u0430\u044f\u043d\u0445\u043e\u043d\u0433\u043e\u0440"
    ],
    "name:nld_x_preferred":[
        "Bajanhongor"
    ],
    "name:pol_x_preferred":[
        "Bajanchongor"
    ],
    "name:rus_x_preferred":[
        "\u0411\u0430\u044f\u043d\u0445\u043e\u043d\u0433\u043e\u0440"
    ],
    "name:spa_x_preferred":[
        "Bayanhongor"
    ],
    "name:srp_x_preferred":[
        "\u0411\u0430\u0458\u0430\u043d\u0445\u043e\u043d\u0433\u043e\u0440"
    ],
    "name:swe_x_preferred":[
        "Bajanchongor"
    ],
    "name:tur_x_preferred":[
        "Bayanhongor"
    ],
    "name:ukr_x_preferred":[
        "\u0411\u0430\u044f\u043d\u0445\u043e\u043d\u0433\u043e\u0440"
    ],
    "name:unk_x_variant":[
        "Bayan Khonkhor Sume"
    ],
    "name:urd_x_preferred":[
        "\u0628\u06cc\u0627\u0646\u062e\u0648\u0646\u06af\u0648\u0631"
    ],
    "name:vie_x_preferred":[
        "Bayankhongor"
    ],
    "name:war_x_preferred":[
        "Bayankhongor"
    ],
    "name:zho_min_nan_x_preferred":[
        "Bayankhongor"
    ],
    "name:zho_x_preferred":[
        "\u5df4\u5f65\u6d2a\u6208\u723e"
    ],
    "qs:gn_country":"MN",
    "qs:gn_fcode":"PPL",
    "qs:gn_pop":23234,
    "qs:name":"Bayanhongor",
    "qs:name_adm0":"Mongolia",
    "qs:name_adm1":"Bayanhongor",
    "qs:photos":28,
    "qs:photos_1k":6,
    "qs:photos_9k":1,
    "qs:photos_9r":2,
    "qs:photos_all":28,
    "qs:photos_sr":2,
    "qs:placetype":"Town",
    "qs:pop_sr":"7",
    "qs:woe_adm0":23424887,
    "wd:wordcount":148,
    "wof:name":"Bayanhongor",
    "wof:placetype":"locality",
    "wof:population":23234
},
  "geometry": {"coordinates":[100.11667,46.71667],"type":"Point"}
}