{
  "type": "Feature",
  "properties": {
    "gn:admin1_code":"15.0",
    "gn:asciiname":"Ovt",
    "gn:country_code":"MN",
    "gn:dem":1681,
    "gn:feature_class":"P",
    "gn:feature_code":"PPLA2",
    "gn:name":"\u00d6vt",
    "gn:population":0,
    "gn:timezone":"Asia/Ulaanbaatar",
    "iso:country":"MN",
    "name:mon_x_preferred":[
        "\u00d6vt"
    ],
    "name:und_x_variant":[
        "Bat-\u00d6ldziy",
        "Bat-\u00d6ldzi\u00ef"
    ],
    "wof:name":"Ovt",
    "wof:placetype":"locality"
},
  "geometry": {"coordinates":[102.25,46.81667],"type":"Point"}
}