{
  "type": "Feature",
  "properties": {
    "gn:admin1_code":"13",
    "gn:asciiname":"Hilganatayn Huryee",
    "gn:cc2":"MN",
    "gn:country_code":"MN",
    "gn:dem":1352,
    "gn:feature_class":"P",
    "gn:feature_code":"PPL",
    "gn:name":"Hilganatayn H\u00fcryee",
    "gn:population":0,
    "gn:timezone":"Asia/Ulaanbaatar",
    "iso:country":"MN",
    "name:und_x_variant":[
        "Khilgantuin Khure",
        "Hilganatayn-H\u00fcree",
        "Hilganatayn H\u00fcryee"
    ],
    "wof:name":"Hilganatayn Huryee",
    "wof:placetype":"locality"
},
  "geometry": {"coordinates":[101.09999999999999,49.21667],"type":"Point"}
}