{
  "type": "Feature",
  "properties": {
    "gn:admin1_code":"18",
    "gn:asciiname":"Boro Ondor Hiid",
    "gn:cc2":"MN",
    "gn:country_code":"MN",
    "gn:dem":1287,
    "gn:feature_class":"P",
    "gn:feature_code":"PPL",
    "gn:name":"Boro \u00d6nd\u00f6r Hiid",
    "gn:population":0,
    "gn:timezone":"Asia/Ulaanbaatar",
    "iso:country":"MN",
    "name:und_x_variant":[
        "Boro Undur Khid",
        "Boro \u00d6nd\u00f6r Hiid"
    ],
    "wof:name":"Boro Ondor Hiid",
    "wof:placetype":"locality"
},
  "geometry": {"coordinates":[106.03333000000001,47.41667],"type":"Point"}
}