{
  "type": "Feature",
  "properties": {
    "gn:admin1_code":"16.0",
    "gn:asciiname":"Sharingol",
    "gn:country_code":"MN",
    "gn:dem":904,
    "gn:feature_class":"P",
    "gn:feature_code":"PPLA2",
    "gn:name":"Shar\u00efngol",
    "gn:population":0,
    "gn:timezone":"Asia/Ulaanbaatar",
    "iso:country":"MN",
    "wof:name":"Sharingol",
    "wof:placetype":"locality"
},
  "geometry": {"coordinates":[106.43004999999999,49.23733],"type":"Point"}
}