{
  "type": "Feature",
  "properties": {
    "gn:admin1_code":"17",
    "gn:asciiname":"Hongor",
    "gn:cc2":"MN",
    "gn:country_code":"MN",
    "gn:dem":886,
    "gn:feature_class":"P",
    "gn:feature_code":"PPL",
    "gn:name":"Hongor",
    "gn:population":0,
    "gn:timezone":"Asia/Choibalsan",
    "iso:country":"MN",
    "name:ceb_x_preferred":[
        "Hongor"
    ],
    "name:swe_x_preferred":[
        "Hongor"
    ],
    "name:und_x_variant":[
        "Khongor",
        "Hongor Suma",
        "Khongor Somon",
        "Hongoru",
        "Mandal-Somon",
        "Hongor sumu"
    ],
    "wof:name":"Hongor",
    "wof:placetype":"locality"
},
  "geometry": {"coordinates":[112.73333,45.78333],"type":"Point"}
}