{
  "type": "Feature",
  "properties": {
    "gn:admin1_code":"24",
    "gn:asciiname":"Eligen Deese",
    "gn:cc2":"MN",
    "gn:country_code":"MN",
    "gn:dem":1196,
    "gn:feature_class":"P",
    "gn:feature_code":"PPL",
    "gn:name":"Eligen Deese",
    "gn:population":0,
    "gn:timezone":"Asia/Ulaanbaatar",
    "iso:country":"MN",
    "name:und_x_variant":[
        "Eligen Des",
        "Eligen Deese"
    ],
    "wof:name":"Eligen Deese",
    "wof:placetype":"locality"
},
  "geometry": {"coordinates":[109.05,46.85],"type":"Point"}
}