{
  "type": "Feature",
  "properties": {
    "gn:admin1_code":"9.0",
    "gn:asciiname":"Narangiin Dugang",
    "gn:cc2":"MN",
    "gn:country_code":"MN",
    "gn:dem":2001,
    "gn:feature_class":"P",
    "gn:feature_code":"PPL",
    "gn:name":"Narangiin Dugang",
    "gn:population":0,
    "gn:timezone":"Asia/Hovd",
    "iso:country":"MN",
    "name:und_x_variant":[
        "Naringiin dugang",
        "Narangiin Dugang"
    ],
    "wof:name":"Narangiin Dugang",
    "wof:placetype":"locality"
},
  "geometry": {"coordinates":[96.08333,48.95],"type":"Point"}
}