{
  "type": "Feature",
  "properties": {
    "gn:admin1_code":"08",
    "gn:asciiname":"Hashaat",
    "gn:cc2":"MN",
    "gn:country_code":"MN",
    "gn:dem":1463,
    "gn:feature_class":"P",
    "gn:feature_code":"PPLA2",
    "gn:name":"Hashaat",
    "gn:population":0,
    "gn:timezone":"Asia/Ulaanbaatar",
    "iso:country":"MN",
    "name:und_x_variant":[
        "Del'ger-khangay",
        "Delger Khangay Somon",
        "Delger Khangai",
        "Delger Hangay Suma",
        "Delgerhangay",
        "Delger hangay sumu",
        "Deleger Khangai Somon",
        "Derigeru-hangai",
        "Delger Khaigay Somon"
    ],
    "wof:name":"Hashaat",
    "wof:placetype":"locality"
},
  "geometry": {"coordinates":[104.80511,45.24323],"type":"Point"}
}