{
  "type": "Feature",
  "properties": {
    "gn:admin1_code":"13",
    "gn:asciiname":"Bugdegenii Huryee",
    "gn:cc2":"MN",
    "gn:country_code":"MN",
    "gn:dem":1857,
    "gn:feature_class":"P",
    "gn:feature_code":"PPL",
    "gn:name":"B\u00fcgdegenii H\u00fcryee",
    "gn:population":0,
    "gn:timezone":"Asia/Ulaanbaatar",
    "iso:country":"MN",
    "name:und_x_variant":[
        "Bugdegeni khure",
        "B\u00fcgdegenii H\u00fcryee"
    ],
    "wof:name":"Bugdegenii Huryee",
    "wof:placetype":"locality"
},
  "geometry": {"coordinates":[100.05,49.13333],"type":"Point"}
}