{
  "type": "Feature",
  "properties": {
    "gn:admin1_code":"14.0",
    "gn:asciiname":"Tsagaan Deresenii Hural",
    "gn:cc2":"MN",
    "gn:country_code":"MN",
    "gn:dem":1680,
    "gn:feature_class":"P",
    "gn:feature_code":"PPL",
    "gn:name":"Tsagaan Deresenii Hural",
    "gn:population":0,
    "gn:timezone":"Asia/Ulaanbaatar",
    "iso:country":"MN",
    "name:und_x_variant":[
        "Tsagan derisuni khural",
        "Tsagaan Deresenii Hural"
    ],
    "wof:name":"Tsagaan Deresenii Hural",
    "wof:placetype":"locality"
},
  "geometry": {"coordinates":[103.16667,43.35],"type":"Point"}
}