{
  "type": "Feature",
  "properties": {
    "gn:admin1_code":"01",
    "gn:asciiname":"Hooltoyn Dugang",
    "gn:cc2":"MN",
    "gn:country_code":"MN",
    "gn:dem":1785,
    "gn:feature_class":"P",
    "gn:feature_code":"PPL",
    "gn:name":"Hooltoyn Dugang",
    "gn:population":0,
    "gn:timezone":"Asia/Ulaanbaatar",
    "iso:country":"MN",
    "name:und_x_variant":[
        "Kholtuin dugang",
        "Hoo Hoyn-Dugan",
        "Hooltoyn Dugang"
    ],
    "wof:name":"Hooltoyn Dugang",
    "wof:placetype":"locality"
},
  "geometry": {"coordinates":[100.41667,48.73333],"type":"Point"}
}