{
  "type": "Feature",
  "properties": {
    "gn:admin1_code":"6.0",
    "gn:asciiname":"Onon",
    "gn:cc2":"MN",
    "gn:country_code":"MN",
    "gn:dem":892,
    "gn:feature_class":"P",
    "gn:feature_code":"PPL",
    "gn:name":"Onon",
    "gn:population":0,
    "gn:timezone":"Asia/Choibalsan",
    "iso:country":"MN",
    "name:ceb_x_preferred":[
        "Onon"
    ],
    "name:ces_x_preferred":[
        "Onon"
    ],
    "name:kat_x_preferred":[
        "\u10dd\u10dc\u10dd\u10dc\u10d8"
    ],
    "name:mon_x_preferred":[
        "\u041e\u043d\u043e\u043d"
    ],
    "name:por_x_preferred":[
        "Onon"
    ],
    "name:slv_x_preferred":[
        "Onon"
    ],
    "name:swe_x_preferred":[
        "Onon"
    ],
    "name:ukr_x_preferred":[
        "\u041e\u043d\u043e\u043d"
    ],
    "name:und_x_variant":[
        "Uuldza",
        "Ul\u2019dza",
        "Onon"
    ],
    "wof:name":"Onon",
    "wof:placetype":"locality"
},
  "geometry": {"coordinates":[112.66667,49.11667],"type":"Point"}
}