{
  "type": "Feature",
  "properties": {
    "gn:admin1_code":"08",
    "gn:asciiname":"Dzuun Ganjir Hiid",
    "gn:cc2":"MN",
    "gn:country_code":"MN",
    "gn:dem":1343,
    "gn:feature_class":"P",
    "gn:feature_code":"PPL",
    "gn:name":"Dz\u00fc\u00fcn Ganjir Hiid",
    "gn:population":0,
    "gn:timezone":"Asia/Ulaanbaatar",
    "iso:country":"MN",
    "name:und_x_variant":[
        "Tszun ganchzhur khid",
        "Dz\u00fc\u00fcn Ganjir Hiid"
    ],
    "wof:name":"Dzuun Ganjir Hiid",
    "wof:placetype":"locality"
},
  "geometry": {"coordinates":[107.55,45.81667],"type":"Point"}
}