{
  "type": "Feature",
  "properties": {
    "gn:admin1_code":"6.0",
    "gn:asciiname":"Ulan-Tsereg",
    "gn:country_code":"MN",
    "gn:dem":680,
    "gn:feature_class":"P",
    "gn:feature_code":"PPL",
    "gn:name":"Ulan-Tsereg",
    "gn:population":0,
    "gn:timezone":"Asia/Choibalsan",
    "iso:country":"MN",
    "wof:name":"Ulan-Tsereg",
    "wof:placetype":"locality"
},
  "geometry": {"coordinates":[115.59999999999999,47.45],"type":"Point"}
}