{
  "type": "Feature",
  "properties": {
    "gn:admin1_code":"17",
    "gn:asciiname":"Hongor",
    "gn:cc2":"MN",
    "gn:country_code":"MN",
    "gn:dem":1247,
    "gn:feature_class":"P",
    "gn:feature_code":"PPLA2",
    "gn:name":"Hongor",
    "gn:population":0,
    "gn:timezone":"Asia/Choibalsan",
    "iso:country":"MN",
    "name:ceb_x_preferred":[
        "Hongor"
    ],
    "name:swe_x_preferred":[
        "Hongor"
    ],
    "name:und_x_variant":[
        "Naran"
    ],
    "wof:name":"Hongor",
    "wof:placetype":"locality"
},
  "geometry": {"coordinates":[113.68378,45.13507],"type":"Point"}
}