{
  "type": "Feature",
  "properties": {
    "gn:admin1_code":"16",
    "gn:asciiname":"Buural",
    "gn:cc2":"MN",
    "gn:country_code":"MN",
    "gn:dem":702,
    "gn:feature_class":"P",
    "gn:feature_code":"PPL",
    "gn:name":"Buural",
    "gn:population":0,
    "gn:timezone":"Asia/Ulaanbaatar",
    "iso:country":"MN",
    "name:eng_x_preferred":[
        "Buural"
    ],
    "name:rus_x_preferred":[
        "\u0425\u043e\u043d\u0433\u043e\u0440"
    ],
    "name:und_x_variant":[
        "Hongor"
    ],
    "wof:name":"Buural",
    "wof:placetype":"locality"
},
  "geometry": {"coordinates":[105.96245,49.43598],"type":"Point"}
}