{
  "type": "Feature",
  "properties": {
    "gn:admin1_code":"14.0",
    "gn:asciiname":"Tsagaan Subarga Hural",
    "gn:cc2":"MN",
    "gn:country_code":"MN",
    "gn:dem":1701,
    "gn:feature_class":"P",
    "gn:feature_code":"PPL",
    "gn:name":"Tsagaan Subarga Hural",
    "gn:population":0,
    "gn:timezone":"Asia/Ulaanbaatar",
    "iso:country":"MN",
    "name:und_x_variant":[
        "Tsagan-Suburgani-Khural",
        "Tsagaansurvaga",
        "Tsagan suburga khural",
        "Tsagaan Suwraga Hural",
        "Tsagaan suburga\u2019in hural",
        "Tsagaan suburgan\u2019i hural",
        "Tsagaan Subarga Hural"
    ],
    "wof:name":"Tsagaan Subarga Hural",
    "wof:placetype":"locality"
},
  "geometry": {"coordinates":[102.19222000000001,43.60083],"type":"Point"}
}