{
  "type": "Feature",
  "properties": {
    "gn:admin1_code":"17",
    "gn:asciiname":"Darhanhaan",
    "gn:cc2":"MN",
    "gn:country_code":"MN",
    "gn:dem":901,
    "gn:feature_class":"P",
    "gn:feature_code":"PPL",
    "gn:name":"Darhanhaan",
    "gn:population":0,
    "gn:timezone":"Asia/Choibalsan",
    "iso:country":"MN",
    "name:und_x_variant":[
        "Darkhankhaan",
        "Darhanhaan"
    ],
    "wof:name":"Darhanhaan",
    "wof:placetype":"locality"
},
  "geometry": {"coordinates":[113.86667,46.76667],"type":"Point"}
}