{
  "type": "Feature",
  "properties": {
    "gn:admin1_code":"16",
    "gn:asciiname":"Holor",
    "gn:cc2":"MN",
    "gn:country_code":"MN",
    "gn:dem":846,
    "gn:feature_class":"P",
    "gn:feature_code":"PPL",
    "gn:name":"Holor",
    "gn:population":0,
    "gn:timezone":"Asia/Ulaanbaatar",
    "iso:country":"MN",
    "name:und_x_variant":[
        "Kholar",
        "Holor"
    ],
    "wof:name":"Holor",
    "wof:placetype":"locality"
},
  "geometry": {"coordinates":[105.66667,49.33333],"type":"Point"}
}