{
  "type": "Feature",
  "properties": {
    "gn:admin1_code":"20",
    "gn:asciiname":"Nalayh",
    "gn:cc2":"MN",
    "gn:country_code":"MN",
    "gn:dem":1434,
    "gn:feature_class":"P",
    "gn:feature_code":"PPL",
    "gn:name":"Nalayh",
    "gn:population":0,
    "gn:timezone":"Asia/Ulaanbaatar",
    "iso:country":"MN",
    "name:ceb_x_preferred":[
        "Nalayh"
    ],
    "name:deu_x_preferred":[
        "Nalaich"
    ],
    "name:fas_x_preferred":[
        "\u0646\u0627\u0644\u0627\u06cc\u062e"
    ],
    "name:fra_x_preferred":[
        "Nalayh"
    ],
    "name:hin_x_preferred":[
        "\u0928\u093e\u0932\u093e\u0907\u0916"
    ],
    "name:ita_x_preferred":[
        "Nalajh"
    ],
    "name:lit_x_preferred":[
        "Nalaichas"
    ],
    "name:mkd_x_preferred":[
        "\u041d\u0430\u043b\u0430\u0458\u0445"
    ],
    "name:mon_x_preferred":[
        "\u041d\u0430\u043b\u0430\u0439\u0445"
    ],
    "name:nor_x_preferred":[
        "Nalajkh"
    ],
    "name:pol_x_preferred":[
        "Nalajch"
    ],
    "name:rus_x_preferred":[
        "\u041d\u0430\u043b\u0430\u0439\u0445"
    ],
    "name:swe_x_preferred":[
        "Nalayh"
    ],
    "name:tur_x_preferred":[
        "Nalayh"
    ],
    "name:ukr_x_preferred":[
        "\u041d\u0430\u043b\u0430\u0439\u0445"
    ],
    "name:und_x_variant":[
        "Nalaykha",
        "Nalayha",
        "Nala\u00efkh",
        "Nalaikha",
        "Naraiha",
        "Na-lai-ha",
        "Nalaykhu",
        "Nalayh"
    ],
    "name:urd_x_preferred":[
        "\u0646\u0627\u0644\u0627\u06cc\u062e"
    ],
    "name:vie_x_preferred":[
        "Nalaikh"
    ],
    "name:zho_x_preferred":[
        "\u7eb3\u6765\u54c8\u533a"
    ],
    "wof:name":"Nalayh",
    "wof:placetype":"locality"
},
  "geometry": {"coordinates":[107.28333000000001,47.76667],"type":"Point"}
}