{
  "type": "Feature",
  "properties": {
    "gn:admin1_code":"20",
    "gn:asciiname":"Nalayh",
    "gn:cc2":"MN",
    "gn:country_code":"MN",
    "gn:dem":1434,
    "gn:feature_class":"P",
    "gn:feature_code":"PPL",
    "gn:name":"Nalayh",
    "gn:population":0,
    "gn:timezone":"Asia/Ulaanbaatar",
    "iso:country":"MN",
    "name:und_x_variant":[
        "Nalaykha",
        "Nalayha",
        "Nala\u00efkh",
        "Nalaikha",
        "Naraiha",
        "Na-lai-ha",
        "Nalaykhu",
        "Nalayh"
    ],
    "wof:name":"Nalayh",
    "wof:placetype":"locality"
},
  "geometry": {"coordinates":[107.28333000000001,47.76667],"type":"Point"}
}