{
  "type": "Feature",
  "properties": {
    "gn:admin1_code":"10.0",
    "gn:asciiname":"Bayan",
    "gn:cc2":"MN",
    "gn:country_code":"MN",
    "gn:dem":1848,
    "gn:feature_class":"P",
    "gn:feature_code":"PPLA2",
    "gn:name":"Bayan",
    "gn:population":0,
    "gn:timezone":"Asia/Hovd",
    "iso:country":"MN",
    "name:und_x_variant":[
        "Bayan uula sumu",
        "Bayan-Ula",
        "Bayan-Uul",
        "Bayan uula",
        "Bayan Uula Suma",
        "Bayan Ula Somon"
    ],
    "wof:name":"Bayan",
    "wof:placetype":"locality"
},
  "geometry": {"coordinates":[95.19962,46.9929],"type":"Point"}
}