{
  "type": "Feature",
  "properties": {
    "gn:admin1_code":"21",
    "gn:asciiname":"Bayangol",
    "gn:country_code":"MN",
    "gn:dem":978,
    "gn:feature_class":"P",
    "gn:feature_code":"PPL",
    "gn:name":"Bayangol",
    "gn:population":0,
    "gn:timezone":"Asia/Ulaanbaatar",
    "iso:country":"MN",
    "name:ceb_x_preferred":[
        "Bayangol"
    ],
    "name:deu_x_preferred":[
        "Bajangol"
    ],
    "name:fra_x_preferred":[
        "Bayangol"
    ],
    "name:mon_x_preferred":[
        "\u0411\u0430\u044f\u043d\u0433\u043e\u043b \u0441\u0443\u043c"
    ],
    "name:rus_x_preferred":[
        "\u0411\u0430\u044f\u043d\u0433\u043e\u043b"
    ],
    "name:swe_x_preferred":[
        "Bayangol"
    ],
    "wof:name":"Bayangol",
    "wof:placetype":"locality"
},
  "geometry": {"coordinates":[103.66667,49.51667],"type":"Point"}
}