{
  "type": "Feature",
  "properties": {
    "gn:admin1_code":"14.0",
    "gn:asciiname":"Tsagaan Uulaiin Sume",
    "gn:cc2":"MN",
    "gn:country_code":"MN",
    "gn:dem":1274,
    "gn:feature_class":"P",
    "gn:feature_code":"PPL",
    "gn:name":"Tsagaan Uulaiin S\u00fcme",
    "gn:population":0,
    "gn:timezone":"Asia/Ulaanbaatar",
    "iso:country":"MN",
    "name:und_x_variant":[
        "Tsagan Ulain Sume",
        "Tsagaan Ulaan S\u00fcme",
        "Tsagan-Ulyn-Sume",
        "Tsagaan Uulaiin S\u00fcme"
    ],
    "wof:name":"Tsagaan Uulaiin Sume",
    "wof:placetype":"locality"
},
  "geometry": {"coordinates":[103.25,41.98333],"type":"Point"}
}