{
  "type": "Feature",
  "properties": {
    "gn:admin1_code":"07",
    "gn:asciiname":"Budargaiin Hural",
    "gn:cc2":"MN",
    "gn:country_code":"MN",
    "gn:dem":1072,
    "gn:feature_class":"P",
    "gn:feature_code":"PPL",
    "gn:name":"Budargaiin Hural",
    "gn:population":0,
    "gn:timezone":"Asia/Ulaanbaatar",
    "iso:country":"MN",
    "name:und_x_variant":[
        "Budarg\u00f6in Khural",
        "Budargin Khural",
        "Budargyin khural",
        "Budargaiin Hural"
    ],
    "wof:name":"Budargaiin Hural",
    "wof:placetype":"locality"
},
  "geometry": {"coordinates":[110.66667,45.58333],"type":"Point"}
}