{
  "type": "Feature",
  "properties": {
    "gn:admin1_code":"18",
    "gn:asciiname":"Bagahangay",
    "gn:country_code":"MN",
    "gn:dem":1464,
    "gn:feature_class":"P",
    "gn:feature_code":"PPL",
    "gn:name":"Bagahangay",
    "gn:population":0,
    "gn:timezone":"Asia/Ulaanbaatar",
    "iso:country":"MN",
    "wof:name":"Bagahangay",
    "wof:placetype":"locality"
},
  "geometry": {"coordinates":[107.43702,47.35232],"type":"Point"}
}