{
  "type": "Feature",
  "properties": {
    "gn:admin1_code":"06",
    "gn:asciiname":"Lamaiin Hiid",
    "gn:cc2":"MN",
    "gn:country_code":"MN",
    "gn:dem":710,
    "gn:feature_class":"P",
    "gn:feature_code":"PPL",
    "gn:name":"Lamaiin Hiid",
    "gn:population":0,
    "gn:timezone":"Asia/Choibalsan",
    "iso:country":"MN",
    "name:und_x_variant":[
        "Lam\u00f6yn Khid",
        "Lamyin-Khid",
        "Lamyyn Khid",
        "Lamaiin Hiid"
    ],
    "wof:name":"Lamaiin Hiid",
    "wof:placetype":"locality"
},
  "geometry": {"coordinates":[114.86667,48.23333],"type":"Point"}
}