{
  "type": "Feature",
  "properties": {
    "gn:admin1_code":"13.0",
    "gn:asciiname":"Altraga",
    "gn:cc2":"MN",
    "gn:country_code":"MN",
    "gn:dem":1617,
    "gn:feature_class":"P",
    "gn:feature_code":"PPLA2",
    "gn:name":"Altraga",
    "gn:population":0,
    "gn:timezone":"Asia/Ulaanbaatar",
    "iso:country":"MN",
    "name:eng_x_preferred":[
        "Altraga"
    ],
    "name:rus_x_preferred":[
        "\u0411\u0430\u044f\u043d-\u0414\u0437\u0443\u0440\u0445"
    ],
    "name:und_x_variant":[
        "Bayan Dz\u00fcrihe Suma",
        "Bayandz\u00fcrh",
        "Bayandz\u00fcrkh"
    ],
    "wof:name":"Altraga",
    "wof:placetype":"locality"
},
  "geometry": {"coordinates":[98.97205,50.1791],"type":"Point"}
}