{
  "type": "Feature",
  "properties": {
    "gn:admin1_code":"18",
    "gn:asciiname":"Hereleng Dugang",
    "gn:cc2":"MN",
    "gn:country_code":"MN",
    "gn:dem":1515,
    "gn:feature_class":"P",
    "gn:feature_code":"PPL",
    "gn:name":"Hereleng Dugang",
    "gn:population":0,
    "gn:timezone":"Asia/Ulaanbaatar",
    "iso:country":"MN",
    "name:und_x_variant":[
        "Kherulun-Dugan",
        "Herlen Dugan",
        "Kherulun-dugang",
        "Kherlen dugang",
        "Hereleng Dugang"
    ],
    "wof:name":"Hereleng Dugang",
    "wof:placetype":"locality"
},
  "geometry": {"coordinates":[108.96666999999999,48.35],"type":"Point"}
}