{
  "type": "Feature",
  "properties": {
    "gn:admin1_code":"02",
    "gn:asciiname":"Bayanhongor",
    "gn:country_code":"MN",
    "gn:dem":1873,
    "gn:feature_class":"P",
    "gn:feature_code":"PPLA",
    "gn:name":"Bayanhongor",
    "gn:population":26252,
    "gn:timezone":"Asia/Ulaanbaatar",
    "iso:country":"MN",
    "name:mon_x_preferred":[
        "\u0411\u0430\u044f\u043d\u0445\u043e\u043d\u0433\u043e\u0440"
    ],
    "name:mon_x_variant":[
        "Bayanhongor"
    ],
    "name:und_x_variant":[
        "Youth City",
        "Dzaluuchuud"
    ],
    "wof:name":"Bayanhongor",
    "wof:placetype":"locality",
    "wof:population":26252
},
  "geometry": {"coordinates":[100.71805999999999,46.19444],"type":"Point"}
}