{
  "type": "Feature",
  "properties": {
    "gn:admin1_code":"18",
    "gn:asciiname":"Mandal",
    "gn:cc2":"MN",
    "gn:country_code":"MN",
    "gn:dem":1127,
    "gn:feature_class":"P",
    "gn:feature_code":"PPLA2",
    "gn:name":"Mandal",
    "gn:population":0,
    "gn:timezone":"Asia/Ulaanbaatar",
    "iso:country":"MN",
    "name:ceb_x_preferred":[
        "Bats\u00fcmber"
    ],
    "name:mkd_x_preferred":[
        "\u0411\u0430\u0446\u0443\u043c\u0431\u0435\u0440"
    ],
    "name:mon_x_preferred":[
        "\u0411\u0430\u0442\u0441\u04af\u043c\u0431\u044d\u0440 \u0441\u0443\u043c"
    ],
    "name:rus_x_preferred":[
        "\u0411\u0430\u0442\u0441\u0443\u043c\u0431\u044d\u0440"
    ],
    "name:swe_x_preferred":[
        "Bats\u00fcmber"
    ],
    "name:ukr_x_preferred":[
        "\u0411\u0430\u0442\u0441\u0443\u043c\u0431\u0435\u0440"
    ],
    "name:und_x_variant":[
        "Bata S\u00fcmber Suma",
        "Batu-Sumbur",
        "Batu Sumbur Somon",
        "Batur Sumbur Sume",
        "Batu s\u00fcmb\u00fcr sumu",
        "Bata S\u00fcmber Somon",
        "Bats\u00fcmber"
    ],
    "wof:name":"Mandal",
    "wof:placetype":"locality"
},
  "geometry": {"coordinates":[106.74075999999999,48.37062],"type":"Point"}
}