{
  "type": "Feature",
  "properties": {
    "gn:admin1_code":"18",
    "gn:asciiname":"Jalmaiin",
    "gn:cc2":"MN",
    "gn:country_code":"MN",
    "gn:dem":1839,
    "gn:feature_class":"P",
    "gn:feature_code":"PPL",
    "gn:name":"Jalmaiin",
    "gn:population":0,
    "gn:timezone":"Asia/Ulaanbaatar",
    "iso:country":"MN",
    "name:und_x_variant":[
        "Dzhalmyn",
        "Jalm\u00f6n",
        "Jalmaiin"
    ],
    "wof:name":"Jalmaiin",
    "wof:placetype":"locality"
},
  "geometry": {"coordinates":[107.86667,48.15],"type":"Point"}
}