{
  "type": "Feature",
  "properties": {
    "gn:admin1_code":"01",
    "gn:asciiname":"Bugat",
    "gn:cc2":"MN",
    "gn:country_code":"MN",
    "gn:dem":1941,
    "gn:feature_class":"P",
    "gn:feature_code":"PPL",
    "gn:name":"Bugat",
    "gn:population":0,
    "gn:timezone":"Asia/Ulaanbaatar",
    "iso:country":"MN",
    "name:ceb_x_preferred":[
        "Bugat"
    ],
    "name:fra_x_preferred":[
        "Bugat"
    ],
    "name:mon_x_preferred":[
        "\u0411\u0443\u0433\u0430\u0442 \u0441\u0443\u043c"
    ],
    "name:rus_x_preferred":[
        "\u0411\u0443\u0433\u0430\u0442"
    ],
    "name:swe_x_preferred":[
        "Bugat"
    ],
    "name:ukr_x_preferred":[
        "\u0411\u0443\u0433\u0430\u0442"
    ],
    "name:und_x_variant":[
        "Bugutu",
        "Bugata Suma",
        "Bugutu Sumu",
        "Bugutu Somon",
        "Bugata",
        "Bugat"
    ],
    "wof:name":"Bugat",
    "wof:placetype":"locality"
},
  "geometry": {"coordinates":[101.26667,47.91667],"type":"Point"}
}