{
  "type": "Feature",
  "properties": {
    "gn:admin1_code":"21",
    "gn:asciiname":"Dzuun Guunii Huryee",
    "gn:cc2":"MN",
    "gn:country_code":"MN",
    "gn:dem":1368,
    "gn:feature_class":"P",
    "gn:feature_code":"PPL",
    "gn:name":"Dz\u00fc\u00fcn Guunii H\u00fcryee",
    "gn:population":0,
    "gn:timezone":"Asia/Ulaanbaatar",
    "iso:country":"MN",
    "name:und_x_variant":[
        "Tszun-gunyy khure",
        "Dzun gunyy khure",
        "Dz\u00fc\u00fcn Guunii H\u00fcryee"
    ],
    "wof:name":"Dzuun Guunii Huryee",
    "wof:placetype":"locality"
},
  "geometry": {"coordinates":[103.83333,48.26667],"type":"Point"}
}