{
  "type": "Feature",
  "properties": {
    "gn:admin1_code":"17",
    "gn:asciiname":"Habhastayn Hiid",
    "gn:cc2":"MN",
    "gn:country_code":"MN",
    "gn:dem":969,
    "gn:feature_class":"P",
    "gn:feature_code":"PPL",
    "gn:name":"Habhastayn Hiid",
    "gn:population":0,
    "gn:timezone":"Asia/Choibalsan",
    "iso:country":"MN",
    "name:und_x_variant":[
        "Khabkhasteyn Khid",
        "Habhastayn Hiid"
    ],
    "wof:name":"Habhastayn Hiid",
    "wof:placetype":"locality"
},
  "geometry": {"coordinates":[113.83333,46.55],"type":"Point"}
}