{
  "type": "Feature",
  "properties": {
    "gn:admin1_code":"12.0",
    "gn:asciiname":"Tsenher",
    "gn:country_code":"MN",
    "gn:dem":2800,
    "gn:feature_class":"P",
    "gn:feature_code":"PPLA2",
    "gn:name":"Tsenher",
    "gn:population":0,
    "gn:timezone":"Asia/Hovd",
    "iso:country":"MN",
    "name:mon_x_preferred":[
        "Tsenher"
    ],
    "name:und_x_variant":[
        "M\u00f6nk\u00f6 Khairkhan Sume",
        "M\u00f6nh\u00f6 hayrhan",
        "M\u00f6nhhayrhan",
        "M\u00f6nh\u00f6 hayrhan sumu",
        "Munkhu Khayrkhan Somon",
        "Munhe-hairuhan",
        "M\u00f6nkhkha\u00efrkhan",
        "Munkhu-khayrkhan",
        "Tsastu Ula Somon",
        "M\u00f6nh\u00f6 Hayrhan Suma",
        "Munkhe-Khayrkhan-Sumu"
    ],
    "wof:name":"Tsenher",
    "wof:placetype":"locality"
},
  "geometry": {"coordinates":[92.11667,46.91667],"type":"Point"}
}