{
  "type": "Feature",
  "properties": {
    "gn:admin1_code":"13",
    "gn:asciiname":"Buren",
    "gn:country_code":"MN",
    "gn:dem":1451,
    "gn:feature_class":"P",
    "gn:feature_code":"PPL",
    "gn:name":"B\u00fcren",
    "gn:population":0,
    "gn:timezone":"Asia/Ulaanbaatar",
    "iso:country":"MN",
    "name:eng_x_preferred":[
        "B\u00fcren"
    ],
    "name:rus_x_preferred":[
        "\u0411\u0443\u0440\u044d\u043d"
    ],
    "name:und_x_variant":[
        "B\u00fcren"
    ],
    "wof:name":"Buren",
    "wof:placetype":"locality"
},
  "geometry": {"coordinates":[100.23333,49.61667],"type":"Point"}
}