{
  "type": "Feature",
  "properties": {
    "gn:admin1_code":"8.0",
    "gn:asciiname":"Tsabchiriin Hiid",
    "gn:cc2":"MN",
    "gn:country_code":"MN",
    "gn:dem":1329,
    "gn:feature_class":"P",
    "gn:feature_code":"PPL",
    "gn:name":"Tsabchiriin Hiid",
    "gn:population":0,
    "gn:timezone":"Asia/Ulaanbaatar",
    "iso:country":"MN",
    "name:und_x_variant":[
        "Ch\u2019a-p\u2019u-ch\u2019ih-erh",
        "Tsabchiryyn khid",
        "Tsabchiriin-Hiyd",
        "Tsabchir\u00f6yn khid",
        "Tsapchir",
        "Tsapuchiru",
        "Tsabchiriin Hiid"
    ],
    "wof:name":"Tsabchiriin Hiid",
    "wof:placetype":"locality"
},
  "geometry": {"coordinates":[104.76667,45.65],"type":"Point"}
}