{
  "type": "Feature",
  "properties": {
    "gn:admin1_code":"2.0",
    "gn:asciiname":"Bulgan",
    "gn:country_code":"MN",
    "gn:dem":2467,
    "gn:feature_class":"P",
    "gn:feature_code":"PPLA2",
    "gn:name":"Bulgan",
    "gn:population":0,
    "gn:timezone":"Asia/Ulaanbaatar",
    "iso:country":"MN",
    "name:ceb_x_preferred":[
        "Bulgan"
    ],
    "name:deu_x_preferred":[
        "Bulgan"
    ],
    "name:fra_x_preferred":[
        "Bulgan"
    ],
    "name:mkd_x_preferred":[
        "\u0411\u0443\u043b\u0433\u0430\u043d"
    ],
    "name:mon_x_preferred":[
        "Bulgan"
    ],
    "name:mon_x_variant":[
        "\u0411\u0443\u043b\u0433\u0430\u043d \u0441\u0443\u043c"
    ],
    "name:rus_x_preferred":[
        "\u0411\u0443\u043b\u0433\u0430\u043d"
    ],
    "name:swe_x_preferred":[
        "Bulgan"
    ],
    "name:ukr_x_preferred":[
        "\u0411\u0443\u043b\u0433\u0430\u043d"
    ],
    "name:und_x_variant":[
        "Bayan-Undur",
        "Bayan undur sumu",
        "Bayan \u00d6nd\u00f6r Suma",
        "Bayan Undur Somon",
        "Bayan-\u00d6nd\u00f6r",
        "Bayan Undur Sume"
    ],
    "name:vie_x_preferred":[
        "Bulgan"
    ],
    "wof:name":"Bulgan",
    "wof:placetype":"locality"
},
  "geometry": {"coordinates":[98.65000000000001,44.78333],"type":"Point"}
}