{
  "type": "Feature",
  "properties": {
    "gn:admin1_code":"24",
    "gn:asciiname":"Bayan Bulagiin Suurin",
    "gn:cc2":"MN",
    "gn:country_code":"MN",
    "gn:dem":1323,
    "gn:feature_class":"P",
    "gn:feature_code":"PPL",
    "gn:name":"Bayan Bulagiin Suurin",
    "gn:population":0,
    "gn:timezone":"Asia/Ulaanbaatar",
    "iso:country":"MN",
    "name:und_x_variant":[
        "Bayan Bulag\u00f6yn Surin",
        "Bayan-Bulag-Hural",
        "Bayan bulagyin surin-khid",
        "Bayan-bulagyyn-surin",
        "Bayan Bulagiin Suurin"
    ],
    "wof:name":"Bayan Bulagiin Suurin",
    "wof:placetype":"locality"
},
  "geometry": {"coordinates":[108.91667,46.66667],"type":"Point"}
}