{
  "type": "Feature",
  "properties": {
    "gn:admin1_code":"17",
    "gn:asciiname":"Burgaasatayn Hamtaral",
    "gn:cc2":"MN",
    "gn:country_code":"MN",
    "gn:dem":1202,
    "gn:feature_class":"P",
    "gn:feature_code":"PPL",
    "gn:name":"Burgaasatayn Hamtaral",
    "gn:population":0,
    "gn:timezone":"Asia/Choibalsan",
    "iso:country":"MN",
    "name:und_x_variant":[
        "Burgastyyn khamtryl",
        "Burgast\u00f6yn Khamtrol",
        "Burgaasatayn Hamtaral"
    ],
    "wof:name":"Burgaasatayn Hamtaral",
    "wof:placetype":"locality"
},
  "geometry": {"coordinates":[112.08333,47.08333],"type":"Point"}
}