{
  "type": "Feature",
  "properties": {
    "gn:admin1_code":"15",
    "gn:asciiname":"Erdene-Dzuu",
    "gn:cc2":"MN",
    "gn:country_code":"MN",
    "gn:dem":1462,
    "gn:feature_class":"P",
    "gn:feature_code":"PPL",
    "gn:name":"Erdene-Dzuu",
    "gn:population":0,
    "gn:timezone":"Asia/Ulaanbaatar",
    "iso:country":"MN",
    "name:und_x_variant":[
        "Cha-yin-k'u-lun",
        "O-erh-t'e-ni-chao",
        "Ch'e-ch'e-li-k'o",
        "Erdenitsou",
        "Erdene-Dzu",
        "Erdeni Juu",
        "Erdenitszu Khure",
        "Erdenitso",
        "Erudenizu",
        "Hsi-k'u-lun",
        "Erdenitszu",
        "Erdeni-tzu",
        "Erdeni Tsu",
        "Erdinidzu",
        "Kure Erdeni-dsu",
        "Erdeni Dzuu",
        "Erdenidzu",
        "Erdeni dzu hure"
    ],
    "wof:name":"Erdene-Dzuu",
    "wof:placetype":"locality"
},
  "geometry": {"coordinates":[102.8425,47.20149],"type":"Point"}
}