{
  "type": "Feature",
  "properties": {
    "gn:admin1_code":"10.0",
    "gn:asciiname":"Sayn-Ust",
    "gn:cc2":"MN",
    "gn:country_code":"MN",
    "gn:dem":1448,
    "gn:feature_class":"P",
    "gn:feature_code":"PPLA2",
    "gn:name":"Sayn-Ust",
    "gn:population":0,
    "gn:timezone":"Asia/Hovd",
    "iso:country":"MN",
    "name:und_x_variant":[
        "Hohmor\u012dt",
        "Khukhu-Moritu Somon",
        "H\u00f6h\u00f6 morit\u00fc",
        "Khukhu-Moritu",
        "H\u00f6h\u00f6 Morito Suma",
        "K\u00f6k\u00f6 M\u00f6ritu Sume",
        "H\u00f6h\u00f6 moritu sumu",
        "Khokhmor't"
    ],
    "wof:name":"Sayn-Ust",
    "wof:placetype":"locality"
},
  "geometry": {"coordinates":[94.52448,47.35732],"type":"Point"}
}