{
  "type": "Feature",
  "properties": {
    "gn:admin1_code":"2.0",
    "gn:asciiname":"Tsorjiin Huryee",
    "gn:cc2":"MN",
    "gn:country_code":"MN",
    "gn:dem":2376,
    "gn:feature_class":"P",
    "gn:feature_code":"PPL",
    "gn:name":"Tsorjiin H\u00fcryee",
    "gn:population":0,
    "gn:timezone":"Asia/Ulaanbaatar",
    "iso:country":"MN",
    "name:und_x_variant":[
        "Tsorchzhiin khure",
        "Tsorzhiin Khure",
        "Tsorjiin H\u00fcryee"
    ],
    "wof:name":"Tsorjiin Huryee",
    "wof:placetype":"locality"
},
  "geometry": {"coordinates":[98.40000000000001,46.51667],"type":"Point"}
}