{
  "type": "Feature",
  "properties": {
    "gn:admin1_code":"01",
    "gn:asciiname":"Burgaasanii Dugang",
    "gn:cc2":"MN",
    "gn:country_code":"MN",
    "gn:dem":1762,
    "gn:feature_class":"P",
    "gn:feature_code":"PPL",
    "gn:name":"Burgaasanii Dugang",
    "gn:population":0,
    "gn:timezone":"Asia/Ulaanbaatar",
    "iso:country":"MN",
    "name:und_x_variant":[
        "Burgaasanii-Dugan",
        "Burgasuni dugang",
        "Burgaasanii Dugang"
    ],
    "wof:name":"Burgaasanii Dugang",
    "wof:placetype":"locality"
},
  "geometry": {"coordinates":[100.95,48.25],"type":"Point"}
}