{
  "type": "Feature",
  "properties": {
    "gn:admin1_code":"13",
    "gn:asciiname":"Jargalant",
    "gn:cc2":"MN",
    "gn:country_code":"MN",
    "gn:dem":1447,
    "gn:feature_class":"P",
    "gn:feature_code":"PPLA2",
    "gn:name":"Jargalant",
    "gn:population":0,
    "gn:timezone":"Asia/Ulaanbaatar",
    "iso:country":"MN",
    "name:und_x_variant":[
        "T\u00f6m\u00f6r bulag Sumu",
        "Tumur-Bulag",
        "T\u00f6m\u00f6r Buluk Sume",
        "Tumur-Bulak Somon",
        "T\u00f6m\u00f6rbulag"
    ],
    "wof:name":"Jargalant",
    "wof:placetype":"locality"
},
  "geometry": {"coordinates":[100.25711,49.29591],"type":"Point"}
}