{
  "type": "Feature",
  "properties": {
    "gn:admin1_code":"21.0",
    "gn:asciiname":"Yiheteyn Dugang",
    "gn:cc2":"MN",
    "gn:country_code":"MN",
    "gn:dem":807,
    "gn:feature_class":"P",
    "gn:feature_code":"PPL",
    "gn:name":"Yiheteyn Dugang",
    "gn:population":0,
    "gn:timezone":"Asia/Ulaanbaatar",
    "iso:country":"MN",
    "name:und_x_variant":[
        "Ikhetuin dugang",
        "Yiheteyn Dugang"
    ],
    "wof:name":"Yiheteyn Dugang",
    "wof:placetype":"locality"
},
  "geometry": {"coordinates":[103.86667,49.46667],"type":"Point"}
}