{
  "type": "Feature",
  "properties": {
    "gn:admin1_code":"08",
    "gn:asciiname":"Haraat",
    "gn:country_code":"MN",
    "gn:dem":1381,
    "gn:feature_class":"P",
    "gn:feature_code":"PPLA2",
    "gn:name":"Haraat",
    "gn:population":0,
    "gn:timezone":"Asia/Ulaanbaatar",
    "iso:country":"MN",
    "name:mon_x_preferred":[
        "Haraat"
    ],
    "name:und_x_variant":[
        "Tsagan Delger Somon",
        "Tsagaandelger",
        "Tsagaan del\u2019ger sumu",
        "Tsagan Delger",
        "Tsagaan Delger Suma",
        "Tsagan-Del\u2019ger-Sumu"
    ],
    "wof:name":"Haraat",
    "wof:placetype":"locality"
},
  "geometry": {"coordinates":[107.65000000000001,46.41667],"type":"Point"}
}