{
  "type": "Feature",
  "properties": {
    "gn:admin1_code":"12.0",
    "gn:asciiname":"Togrog",
    "gn:cc2":"MN",
    "gn:country_code":"MN",
    "gn:dem":1350,
    "gn:feature_class":"P",
    "gn:feature_code":"PPLA2",
    "gn:name":"T\u00f6gr\u00f6g",
    "gn:population":0,
    "gn:timezone":"Asia/Hovd",
    "iso:country":"MN",
    "name:ceb_x_preferred":[
        "Manhan"
    ],
    "name:fra_x_preferred":[
        "Mankhan"
    ],
    "name:mkd_x_preferred":[
        "\u041c\u0430\u043d\u0445\u0430\u043d"
    ],
    "name:mon_x_preferred":[
        "\u041c\u0430\u043d\u0445\u0430\u043d \u0441\u0443\u043c"
    ],
    "name:por_x_preferred":[
        "Mankhan"
    ],
    "name:swe_x_preferred":[
        "Manhan"
    ],
    "name:ukr_x_preferred":[
        "\u041c\u0430\u043d\u0445\u0430\u043d"
    ],
    "name:und_x_variant":[
        "Mankhan Somon",
        "Manhan sumu",
        "Mankhan Sume",
        "Mankhan-Sumu",
        "Manhan Suma"
    ],
    "wof:name":"Togrog",
    "wof:placetype":"locality"
},
  "geometry": {"coordinates":[92.22439,47.42414],"type":"Point"}
}