{
  "type": "Feature",
  "properties": {
    "gn:admin1_code":"12.0",
    "gn:asciiname":"Togrog",
    "gn:cc2":"MN",
    "gn:country_code":"MN",
    "gn:dem":1350,
    "gn:feature_class":"P",
    "gn:feature_code":"PPLA2",
    "gn:name":"T\u00f6gr\u00f6g",
    "gn:population":0,
    "gn:timezone":"Asia/Hovd",
    "iso:country":"MN",
    "name:und_x_variant":[
        "Mankhan",
        "Mankhan Somon",
        "Manhan sumu",
        "Mankhan Sume",
        "Mankhan-Sumu",
        "Manhan Suma",
        "Manhan"
    ],
    "wof:name":"Togrog",
    "wof:placetype":"locality"
},
  "geometry": {"coordinates":[92.22439,47.42414],"type":"Point"}
}