{
  "type": "Feature",
  "properties": {
    "gn:admin1_code":"9.0",
    "gn:asciiname":"Dzuer",
    "gn:cc2":"MN",
    "gn:country_code":"MN",
    "gn:dem":1287,
    "gn:feature_class":"P",
    "gn:feature_code":"PPLA2",
    "gn:name":"Dz\u00fcr",
    "gn:population":0,
    "gn:timezone":"Asia/Hovd",
    "iso:country":"MN",
    "name:und_x_variant":[
        "Tes"
    ],
    "wof:name":"Dzuer",
    "wof:placetype":"locality"
},
  "geometry": {"coordinates":[95.79322999999999,49.65796],"type":"Point"}
}