{
  "type": "Feature",
  "properties": {
    "gn:admin1_code":"13.0",
    "gn:asciiname":"Bugseyn Huryee",
    "gn:cc2":"MN",
    "gn:country_code":"MN",
    "gn:dem":1499,
    "gn:feature_class":"P",
    "gn:feature_code":"PPL",
    "gn:name":"B\u00fcgseyn H\u00fcryee",
    "gn:population":0,
    "gn:timezone":"Asia/Ulaanbaatar",
    "iso:country":"MN",
    "name:und_x_variant":[
        "T\u2019u-kung-sai-yin",
        "Bugseyn Khure",
        "Kure-tugunsein",
        "Bugsein Khure",
        "Bugsey\u2019n hurie",
        "B\u00fcgseyiin H\u00fcrie",
        "B\u00fcgseyn H\u00fcryee"
    ],
    "wof:name":"Bugseyn Huryee",
    "wof:placetype":"locality"
},
  "geometry": {"coordinates":[99.90000000000001,49.53333],"type":"Point"}
}