{
  "type": "Feature",
  "properties": {
    "gn:admin1_code":"15.0",
    "gn:asciiname":"Ulaan-am",
    "gn:country_code":"MN",
    "gn:dem":1783,
    "gn:feature_class":"P",
    "gn:feature_code":"PPL",
    "gn:name":"Ulaan-am",
    "gn:population":0,
    "gn:timezone":"Asia/Ulaanbaatar",
    "iso:country":"MN",
    "wof:name":"Ulaan-am",
    "wof:placetype":"locality"
},
  "geometry": {"coordinates":[103.41667,46.41667],"type":"Point"}
}