{
  "type": "Feature",
  "properties": {
    "gn:admin1_code":"15.0",
    "gn:asciiname":"Noyon Hutagtayn Hiid",
    "gn:cc2":"MN",
    "gn:country_code":"MN",
    "gn:dem":2144,
    "gn:feature_class":"P",
    "gn:feature_code":"PPL",
    "gn:name":"Noyon Hutagtayn Hiid",
    "gn:population":0,
    "gn:timezone":"Asia/Ulaanbaatar",
    "iso:country":"MN",
    "name:und_x_variant":[
        "Noyon Hutagtayn H\u00fcryee",
        "Noyan-Khutukhtuin-Khure",
        "Noyan Khure",
        "Noyan khutukhtiin khid",
        "Noyan hutuhtuin h\u00fcrie",
        "Kumirnya Noyon-khutukhtu",
        "Noyan hutuhtuiin h\u00fcrie",
        "Noyan Hutag Tayn Hiyd",
        "Noyon Hutagtayn Hiid"
    ],
    "wof:name":"Noyon Hutagtayn Hiid",
    "wof:placetype":"locality"
},
  "geometry": {"coordinates":[101.81667,44.76667],"type":"Point"}
}