{
  "type": "Feature",
  "properties": {
    "gn:admin1_code":"1.0",
    "gn:asciiname":"Olon Turagiin Dugang",
    "gn:cc2":"MN",
    "gn:country_code":"MN",
    "gn:dem":1662,
    "gn:feature_class":"P",
    "gn:feature_code":"PPL",
    "gn:name":"Olon Turagiin Dugang",
    "gn:population":0,
    "gn:timezone":"Asia/Ulaanbaatar",
    "iso:country":"MN",
    "name:und_x_variant":[
        "Olon-Turagiin-Dugan",
        "Olon-Turugin dugang",
        "Olon Turagiin Dugang"
    ],
    "wof:name":"Olon Turagiin Dugang",
    "wof:placetype":"locality"
},
  "geometry": {"coordinates":[101.23333,48.15],"type":"Point"}
}