{
  "type": "Feature",
  "properties": {
    "gn:admin1_code":"16.0",
    "gn:asciiname":"Tseregiin Dugang",
    "gn:cc2":"MN",
    "gn:country_code":"MN",
    "gn:dem":636,
    "gn:feature_class":"P",
    "gn:feature_code":"PPL",
    "gn:name":"Tseregiin Dugang",
    "gn:population":0,
    "gn:timezone":"Asia/Ulaanbaatar",
    "iso:country":"MN",
    "name:und_x_variant":[
        "Tserigyin dugang",
        "Tserengiyn-Dugan",
        "Tseregiin Dugang"
    ],
    "wof:name":"Tseregiin Dugang",
    "wof:placetype":"locality"
},
  "geometry": {"coordinates":[106.41667,50.25],"type":"Point"}
}