{
  "type": "Feature",
  "properties": {
    "gn:admin1_code":"18",
    "gn:asciiname":"Ergineg-Hiyd",
    "gn:country_code":"MN",
    "gn:dem":1315,
    "gn:feature_class":"P",
    "gn:feature_code":"PPL",
    "gn:name":"Ergineg-Hiyd",
    "gn:population":0,
    "gn:timezone":"Asia/Ulaanbaatar",
    "iso:country":"MN",
    "wof:name":"Ergineg-Hiyd",
    "wof:placetype":"locality"
},
  "geometry": {"coordinates":[108.08333,46.96667],"type":"Point"}
}