{
  "type": "Feature",
  "properties": {
    "gn:admin1_code":"08",
    "gn:asciiname":"Naran",
    "gn:cc2":"MN",
    "gn:country_code":"MN",
    "gn:dem":1383,
    "gn:feature_class":"P",
    "gn:feature_code":"PPL",
    "gn:name":"Naran",
    "gn:population":0,
    "gn:timezone":"Asia/Ulaanbaatar",
    "iso:country":"MN",
    "name:ceb_x_preferred":[
        "Naran"
    ],
    "name:fas_x_preferred":[
        "\u0646\u0627\u0631\u0627\u0646"
    ],
    "name:swe_x_preferred":[
        "Naran"
    ],
    "name:und_x_variant":[
        "Urto Naran",
        "Nalin",
        "Na-lan",
        "Naran"
    ],
    "wof:name":"Naran",
    "wof:placetype":"locality"
},
  "geometry": {"coordinates":[106.63333,46.56667],"type":"Point"}
}