{
  "type": "Feature",
  "properties": {
    "gn:admin1_code":"21.0",
    "gn:asciiname":"Tsambaiin Hiid",
    "gn:cc2":"MN",
    "gn:country_code":"MN",
    "gn:dem":1020,
    "gn:feature_class":"P",
    "gn:feature_code":"PPL",
    "gn:name":"Tsambaiin Hiid",
    "gn:population":0,
    "gn:timezone":"Asia/Ulaanbaatar",
    "iso:country":"MN",
    "name:und_x_variant":[
        "Tsambayn Khid",
        "Tsambaiin Hiid"
    ],
    "wof:name":"Tsambaiin Hiid",
    "wof:placetype":"locality"
},
  "geometry": {"coordinates":[102.90000000000001,49.65],"type":"Point"}
}