{
  "type": "Feature",
  "properties": {
    "gn:admin1_code":"01",
    "gn:asciiname":"Hujirtayn Sume",
    "gn:country_code":"MN",
    "gn:dem":1748,
    "gn:feature_class":"P",
    "gn:feature_code":"PPL",
    "gn:name":"Hujirtayn S\u00fcme",
    "gn:population":0,
    "gn:timezone":"Asia/Ulaanbaatar",
    "iso:country":"MN",
    "name:und_x_variant":[
        "Khichzhirtuyn Sume",
        "Khuchzhirtuin sume",
        "Hujirtayn S\u00fcme"
    ],
    "wof:name":"Hujirtayn Sume",
    "wof:placetype":"locality"
},
  "geometry": {"coordinates":[101.08333,47.63333],"type":"Point"}
}