{
  "type": "Feature",
  "properties": {
    "gn:admin1_code":"17.0",
    "gn:asciiname":"Shireeteyn Hiid",
    "gn:country_code":"MN",
    "gn:dem":1104,
    "gn:feature_class":"P",
    "gn:feature_code":"PPL",
    "gn:name":"Shireeteyn Hiid",
    "gn:population":0,
    "gn:timezone":"Asia/Choibalsan",
    "iso:country":"MN",
    "wof:name":"Shireeteyn Hiid",
    "wof:placetype":"locality"
},
  "geometry": {"coordinates":[112.34999999999999,45.71667],"type":"Point"}
}