{
  "type": "Feature",
  "properties": {
    "gn:admin1_code":"18.0",
    "gn:asciiname":"Orgil",
    "gn:cc2":"MN",
    "gn:country_code":"MN",
    "gn:dem":1055,
    "gn:feature_class":"P",
    "gn:feature_code":"PPLA2",
    "gn:name":"Orgil",
    "gn:population":0,
    "gn:timezone":"Asia/Ulaanbaatar",
    "iso:country":"MN",
    "name:ceb_x_preferred":[
        "Tseel"
    ],
    "name:mon_x_preferred":[
        "\u0426\u044d\u044d\u043b \u0441\u0443\u043c"
    ],
    "name:rus_x_preferred":[
        "\u0426\u044d\u044d\u043b"
    ],
    "name:swe_x_preferred":[
        "Tseel"
    ],
    "name:und_x_variant":[
        "Tseel"
    ],
    "wof:name":"Orgil",
    "wof:placetype":"locality"
},
  "geometry": {"coordinates":[105.31768999999998,48.4538],"type":"Point"}
}