{
  "type": "Feature",
  "properties": {
    "gn:admin1_code":"8.0",
    "gn:asciiname":"Tavin",
    "gn:cc2":"MN",
    "gn:country_code":"MN",
    "gn:dem":1482,
    "gn:feature_class":"P",
    "gn:feature_code":"PPLA2",
    "gn:name":"Tavin",
    "gn:population":0,
    "gn:timezone":"Asia/Ulaanbaatar",
    "iso:country":"MN",
    "name:und_x_variant":[
        "Adaatsag"
    ],
    "wof:name":"Tavin",
    "wof:placetype":"locality"
},
  "geometry": {"coordinates":[105.73517,46.39194000000001],"type":"Point"}
}