{
  "type": "Feature",
  "properties": {
    "gn:admin1_code":"20",
    "gn:asciiname":"Dzuunmod",
    "gn:cc2":"MN",
    "gn:country_code":"MN",
    "gn:dem":1542,
    "gn:feature_class":"P",
    "gn:feature_code":"PPL",
    "gn:name":"Dzuunmod",
    "gn:population":0,
    "gn:timezone":"Asia/Ulaanbaatar",
    "iso:country":"MN",
    "name:und_x_variant":[
        "Dologon",
        "Sergeleng Suma",
        "Dolon",
        "Doloon",
        "Doron",
        "Sergelen",
        "Dolun",
        "Urto Dolon",
        "Serg\u00fcleng",
        "Doow Luen",
        "Sergeleng",
        "Dosu Luen",
        "Serguleng Sumu",
        "Sergulen Somon",
        "To-lun",
        "To-lung",
        "Dzuunmod"
    ],
    "wof:name":"Dzuunmod",
    "wof:placetype":"locality"
},
  "geometry": {"coordinates":[106.84999999999999,47.78333],"type":"Point"}
}