{
  "type": "Feature",
  "properties": {
    "gn:admin1_code":"12.0",
    "gn:asciiname":"Ulaantolgoy",
    "gn:country_code":"MN",
    "gn:dem":2033,
    "gn:feature_class":"P",
    "gn:feature_code":"PPLA2",
    "gn:name":"Ulaantolgoy",
    "gn:population":0,
    "gn:timezone":"Asia/Hovd",
    "iso:country":"MN",
    "name:ceb_x_preferred":[
        "M\u00f6st"
    ],
    "name:fra_x_preferred":[
        "M\u00f6st"
    ],
    "name:mkd_x_preferred":[
        "\u041c\u043e\u0441\u0442"
    ],
    "name:mon_x_preferred":[
        "Ulaantolgoy"
    ],
    "name:mon_x_variant":[
        "\u041c\u04e9\u0441\u0442 \u0441\u0443\u043c"
    ],
    "name:swe_x_preferred":[
        "M\u00f6st"
    ],
    "name:ukr_x_preferred":[
        "\u041c\u0443\u0441\u0442"
    ],
    "wof:name":"Ulaantolgoy",
    "wof:placetype":"locality"
},
  "geometry": {"coordinates":[92.78333000000001,46.68333],"type":"Point"}
}