{
  "type": "Feature",
  "properties": {
    "gn:admin1_code":"12.0",
    "gn:asciiname":"Ulaantolgoy",
    "gn:country_code":"MN",
    "gn:dem":2033,
    "gn:feature_class":"P",
    "gn:feature_code":"PPLA2",
    "gn:name":"Ulaantolgoy",
    "gn:population":0,
    "gn:timezone":"Asia/Hovd",
    "iso:country":"MN",
    "name:mon_x_preferred":[
        "Ulaantolgoy"
    ],
    "name:und_x_variant":[
        "M\u00f6st"
    ],
    "wof:name":"Ulaantolgoy",
    "wof:placetype":"locality"
},
  "geometry": {"coordinates":[92.78333000000001,46.68333],"type":"Point"}
}